Workbook
Name \aq: #REF!
Name \c: #REF!
Name \e: #REF!
Name \f: #REF!
Name \l: #REF!
Name \p: #REF!
Name \q: #REF!
Name \s: '[1]Originating Station'!#REF!
Name \u: '[1]Originating Station'!#REF!
Name \w: #REF!
Name \x: #REF!
Name \y: '[2]SCADA(MCC-SCC)-Koyali'!#REF!
Name \z: #N/A
Name ____dim4: "$#REF!.$#REF!$#REF!"
Name ____rm4: "$#REF!.$#REF!$#REF!"
Name ___dim4: #REF!
Name ___rm4: #REF!
Name __A1: #REF!
Name __a2: #REF!
Name __a3: #REF!
Name __dim4: "$#REF!.$#REF!$#REF!"
Name __JL91: #N/A
Name __rim4: #REF!
Name __rm4: "$#REF!.$#REF!$#REF!"
Name __xlnm._FilterDatabase: "$#REF!.$B$1:$X$18"
Name _192.168.50.66: #REF!
Name _88: #N/A
Name _A1: #REF!
Name _a2: #REF!
Name _a3: #REF!
Name _BAA1: #REF!
Name _dim4: #REF!
Name _EMC2: #REF!
Name _H264: #REF!
Name _H264FACTOR: #REF!
Name _HRP1001: #REF!
Name _HRP1023: #REF!
Name _HRP1025: #REF!
Name _HRP1026: #REF!
Name _HRP1027: #REF!
Name _HRP1028: #REF!
Name _HRP1035: #REF!
Name _HRP1038: #REF!
Name _HRP1042: #REF!
Name _HRT1035: #REF!
Name _HRT1042: #REF!
Name _JL91: #N/A
Name _MJPEG: #REF!
Name _MJPEGFACTOR: #REF!
Name _MPEG4: #REF!
Name _MPEG4FACTOR: #REF!
Name _PT1001022: #REF!
Name _PT1001022: #REF!
Name _PT1001023: #REF!
Name _PT1001023: #REF!
Name _PT1001025: #REF!
Name _PT1001025: #REF!
Name _PT1001027: #REF!
Name _PT1001031: #REF!
Name _PT1001040: #REF!

Sheet Summary
B3: Sr.No | C3: Function | D3: Total Amount
B4: A | C4: Hardware Cost + AMC | D4: =Working!K20 -> 1.7568551e+08
B7: B | C7: Software Cost | D7: =Working!K48 -> 88333690
B8: Total Cost of Ownership (TCO). | D8: =SUM(D4:D7) -> 2.640192e+08
B10: Assumptions/Consideration
B11: The product and services proposed in this BoM are proposed with OEM standard licenses policy and exclusive of any additional services or Add-Ons offer by the respective OEMs.
B12: Anything that is not mentioned in the proposal/commercial/BoQ/BoM submitted by ESDS at the time of finalization of PO, will not be delivered for whatsoever reason.
B13: In case client requires any new or additional item/service/license except what is mentioned in the proposal, will be charged at additional prices. Rates/Prices & Scope for all such additional/new requirements over and above the BoM/BoQ/Proposal submitted at the time of finalization will be additional and such Rates/Prices & Scope will be submitted to client based on the actual requirement
B14: For any such additional item or service required over and above the the BoM/BoQ/Proposal submitted at the time of finalization, client will have to either raise PO or Confirm over email with acceptance to the new requirement and its applicable charges submitted by ESDS post receiving the additional requirement.
B15: As per the discussion with the Amnex regarding security services, ESDS will only provide Firewall and Antivirus services. If any additional security services mentioned in the RFP are required, they will be managed by Amnex.
B16: In the event of an increase/decrease in the number of resources, additional charges will apply for the adjusted quantities.
B17: Any component or service not specified in the BOM/Commercials is beyond the scope of ESDS.
B18: The product and services proposed in this BoM are proposed with OEM standard licenses policy and exclusive of any additional services or add-Ons offer by the respective OEMs.

Sheet BoM
B1: Sr.No. | C1: Product | D1: Discription | E1: Qty | F1: Total Without GST | G1: With GST
B2: 1 | C2: Physical Server | D2: 2X Intel Xeon Gold 6542Y 24C 250W 2.9GHz Processor, 24X ThinkSystem 64GB TruDDR5 5600MHz (2Rx4) RDIMM, 1X ThinkSystem 440-16i SAS/SATA PCIe Gen4 12Gb Internal HBA, 1X ThinkSystem 2U 8x2.5" SAS/SATA Backplane, 1X Nutanix Flash Node Config, 8X ThinkSystem 2.5" U.3 7500 PRO 7.68TB Read Intensive NVMe PCIe 4.0 x4 HS SSD, 1X ThinkSystem M.2 NVMe 2-Bay RAID Adapter, 2X ThinkSystem M.2 7450 PRO 960GB Read Intensive NVMe PCIe 4.0 x4 NHS SSD 1X ThinkSystem Broadcom 57416 10GBASE-T 2-port OCP Ethernet Adapter, 2X ThinkSystem Broadcom 57414 10/25GbE SFP28 2-port PCIe Ethernet Adapter, 4X SFP+ SR Transceiver, 2X ThinkSystem 1800W 230V Platinum Hot-Swap Gen2 Power Supply, 2X 2.8m, 10A/100-250V, C13 to C14 Jumper Cord (India), 1X TPM 2.0, 1X Enable IPMI-over-LAN, 1X N+N Redundancy With Over-Subscription, 1X G4 x16/x8/x8 PCIe Riser BLKL for Riser 1 Placement, 1X 3Yr Premier 24x7 4Hr Resp ThinkAgile CN HX650 V3 | E2: 8 | F2: ='BID Format'!E33 -> 2.8460343e+08 | G2: ='BID Format'!G33 -> 3.3278835e+08
B3: 2 | C3: Firewall NGFW | D3: Firewall- SONICWALL NSV 470 TOTALSECURE - ADVANCED EDITION 3YR SONICWALL SAAS 365 DAYS OF ADVANCED REPORTING AND ANALYTICS FOR NSV 470 3YR | E3: 2
B4: 3 | C4: Router | D4: Router Cisco Catalyst C8200-1N-4T | E4: 2
B5: 4 | C5: Switch L3 - | D5: Switch L3 Port 24 Port 10 G | E5: 2
B6: 5 | C6: Switch L2 | D6: Switch L2 Port 24 Port 1G | E6: 2
B7: 6 | D7: Caged racks with Physical Security | E7: 2
B8: 7 | C8: WAF | D8: WAF 1 Gbps | E8: 1
B9: 8 | C9: Storage | D9: Storage : Lenovo ThinkSystem DG5200 QLC All Flash Array | E9: 1
B10: 9 | C10: Blackbox | D10: Blackbox | E10: 1
B11: 10 | C11: NAS | D11: NAS Storage - (108TB*3) | E11: 3
B12: 11 | C12: Software | D12: Acropolis Hypervisor | E12: 1
B13: 12 | C13: Software | D13: NCI – PRO :- Nutanix Cloud Infrastructure (NCI) Pro Software License - 3Y subscription | E13: 384
B14: 13 | C14: Software | D14: NCM-Starter :- Nutanix Cloud Manager (NCM) Starter Software License - 3Y subscription | E14: 384
B15: 14 | C15: Software | D15: NCI-ADR :- Nutanix Cloud Infrastructure (NCI) Advanced Replication (DC 352 + DR 384) - 3Y subscription | E15: 736
B16: 15 | C16: OS | D16: Win Server Standard Core SLng LSA OLV 16L NL 3Y Aq Y1 AP | E16: 15
B17: 16 | D17: Exchange Server Ent SLng LSA OLV NL 3Y Aq Y1 AP | E17: 2
B18: 17 | D18: SQL Server Standard Core SLng LSA OLV 2L NL 3Y Aq Y1 AP | E18: 17
B19: 18 | C19: OS | D19: Red Hat Enterprise Linux Server for Service Providers, Full Support (Physical or Virtual Nodes, Dedicated, Yearly) 1st year | E19: 10
B20: 19 | D20: Red Hat Enterprise Linux Server for Service Providers, Diagnostic Support (Physical or Virtual Nodes, Dedicated, Yearly) 1st year | E20: 10
B21: 20 | D21: Red Hat Enterprise Linux, Extended Life Cycle Support Add-On, Layered Support (Physical or Virtual Nodes, Dedicated, Yearly) 1st year | E21: 4
B22: 21 | C22: Service | D22: Migration charges | E22: 1
B23: 22 | C23: AMC | D23: Extended 2Y HW support & 2Y Nutanix License - HX 650 Node | E23: 8
B24: 23 | C24: AMC | D24: Extended 2Y Storage HW support | E24: 1
B25: 24 | C25: Service | D25: SIEM DC Qty. 50 and DR 50 | E25: 1
B26: 25 | C26: Service | D26: SOAR Qty.3 | E26: 1
B27: 26 | C27: Service | D27: EDR -50 VM | E27: 1
B28: 27 | C28: Service | D28: XDR - 50 VM+ Other Devices 15 | E28: 1
B29: 28 | C29: Service | D29: DLP | E29: 50
B30: 29 | C30: Service | D30: PAM Admin User-based License | E30: 5
B31: 30 | C31: Service | D31: PAM End Device | E31: 65
B32: 31 | C32: Service | D32: VAPT - 65 Devices | E32: 1
B33: 32 | C33: Service | D33: VPN | E33: 1
... B46: 45 | C46: Services | D46: DR Drill - 2 Per Year- Each DR Drill will be done either for one Application / number of application, separate DR Drill for One Application will not be done, and if the separate DR drill will be require then additional charges for each DR Drill will be applicable. | E46: 2

Sheet Checklist
B1: Product | C1: OEM | D1: Email | E1: Phone | F1: Compliance | G1: MAF | H1: Local Content Certificate | I1: Price
B2: Lenovo Appliances + Nutanix | C2: Y
B3: Firewall | C3: Checkpoint | D3: riteshb@checkpoint.com
C4: Fortigate | D4: brajgar@fortinet.com
B5: Router | C5: Cisco | D5: vishal.b@inflowtechnologies.com
B6: L3 Switch | C6: Cisco | D6: vishal.b@inflowtechnologies.com
B7: L2 Switch | C7: Cisco | D7: vishal.b@inflowtechnologies.com
B8: WAF | C8: Haldos | D8: kanishk@haltdos.com
C9: Radware | D9: mayurc@radware.com
C10: Imperva | D10: sumit@adviacent.com
B11: SAN | C11: Lenovo
B12: NAS | C12: Lenovo
B13: Blackbox | C13: Comnet
B14: Migration Cost (ComNet)
B15: SIEM | C15: IBM
C16: Gurucul | D16: mandar.inamdar@gurucul.com
C17: Kaspersky | D17: ejaz.shaikh@kaspersky.com
B18: SOAR | C18: Gurucul | D18: mandar.inamdar@gurucul.com
C19: IBM
B20: PIM | C20: Cyberdristi
B21: PAM | C21: Cyberdristi
B22: DLP | C22: Cyberdristi
B23: XDR | C23: Kaspersky | D23: ejaz.shaikh@kaspersky.com
B24: IAM | C24: Cyberdristi
B25: VAPT
B26: IBM SPSS – AMOS version 28 | C26: y
B27: Windows Server + SA Licenses | C27: Y
B28: Exchange 2019 | C28: Y
B29: Exchange SA
B30: Exchange SE
B31: ATP
B32: ECM
B33: SMTP
B34: MSSQL | C34: Y
B35: Redhat Server | C35: Y
B36: Rehat Support | C36: Y
B37: Redhad ELS | C37: Y
B38: Broadband | C38: Y

Sheet Detailed Summary 
C2: Detailed Summary of Overall Cost
C3: S.no | D3: Function | E3: Type | F3: Class/Type of Infrastructure/Function | G3: Quantity | H3: Year 1 | I3: Year 2 | J3: Year 3 | K3: Year 4 | L3: Year 5 | M3: Total (without tax) | N3: Tax Amount | O3: Total With Tax
C4: A. | D4: Managed Services (Domain & Corss Functional Services) Cost
C5: 1 | D5: Server Management | E5: Servers | F5: High Level
C7: 2 | D7: Server Management | E7: Servers | F7: Mid-Level
C9: 3 | D9: Server Management | E9: Servers | F9: Entry Level
C11: 4 | D11: Storage Management | E11: Storage | F11: Enterprise
C13: 5 | D13: Storage Management | E13: Storage | F13: Modular
C15: 6 | D15: Storage Management | E15: SAN Switches | F15: SAN Swicthes
C17: 7 | D17: Backup and restore Services | E17: Backup Device | F17: Tape Library
C19: 8 | D19: Database Management | E19: Database | F19: Critical Applications- production Environment
C21: 9 | D21: Database Management | E21: Database | F21: Non Critical Applications- Production Environment
C23: 10 | D23: Database Management | E23: Database | F23: Non Production Environment
C25: 11 | D25: Network Management | E25: Networks | F25: Routers,L3 Switches,L2 Switches etc,load balancers
D27: Sub Total- Managed Services Cost (A)
C28: B | D28: EMS Cost
C29: S.no | D29: EMS Modules | E29: Product name & version | F29: License Type | G29: No. of Licenses | H29: Year 1 | I29: Year 2 | J29: Year 3 | K29: Year 4 | L29: Year 5 | M29: Total (without tax) | N29: Tax Amount | O29: Total With Tax
C30: 1 | D30: Server Management
C31: 2 | D31: Storage Management
C32: 3 | D32: Data Base Management
C33: 4 | D33: Backup
C34: 5 | D34: Network Management
C35: 6 | D35: SLA Management Module
C36: 7 | D36: Asset and Configuration Management Database (CMDB)
C37: 8 | D37: Service Level Management
C38: 9 | D38: Incident Management
C39: 10 | D39: Problem Management
C40: 11 | D40: Change Management
C41: 12 | D41: Patch Management
... C43: 14 | D43: any other , please specify*
D44: Sub Total- EMS Cost (B)
C45: D. | D45: Infrastructure Cost for EMS Tools
C46: S.No | D46: Hardware/Software Type | E46: Configuration | F46: Quantity required (to be filled by Bidder) | G46: Per Unit Price (Fixed) | H46: Year 1 | I46: Year 2 | J46: Year 3 | K46: Year 4 | L46: Year 5 | M46: Total (without tax) | N46: Tax Amount | O46: Total With Tax
C47: 1 | D47: Server | E47: 2 CPU, Quad Core, 32 GB RAM, | G47: 300000
C48: 2 | D48: Storage | E48: Enterprise Storage | G48: 50000
C49: 3 | D49: OS | E49: Enterprise Version | G49: 40000
C50: 4 | D50: Database | E50: Enterprise Edition | G50: 500000
D51: Sub- Infrastructure Cost for EMS & Helpdesk (D)
C52: E. | D52: Performance Assessment Cost
C53: S.no | D53: Performance Assessment | E53: Frequency | G53: Quantity | H53: Year 1 | I53: Year 2 | J53: Year 3 | K53: Year 4 | L53: Year 5 | M53: Total (without tax) | N53: Tax Amount | O53: Total With Tax
C54: 1 | D54: Performance Analysis for systems – Server OEM | E54: Quarterly | G54: 4
C55: 2 | D55: Storage Assessment Service - Storage OEM | E55: Bi-Annual | G55: 2
C56: 3 | D56: Backup Assessment Service - Storage/Backup OEM | E56: Bi-Annual | G56: 2
C57: 4 | D57: Database Performance Assessment Services | E57: Quarterly | G57: 4
D58: Sub Total- Performance Assessment Cost ( E)
D59: Total (A)+(B)+C)+(D)+( E)

Sheet Sheet3
A1: QRadar Network Insights 1920 specifications
A3: Requirement | B3: Details | C3: Remarks
A4: CPU | B4: 2 x Gold 6354 18 C 3.0 GHz 205 W | C4: https://www.ibm.com/docs/en/qsip/7.5?topic=overview-qradar-network-insights-1920-m7-appliance
A5: Network capture transceivers | B5: 4 x 1 Gb TX Copper SFP transceivers Finisar FCLF8522P2BTL-IG
B6: 4 x 1 Gb SX SFP transceivers Finisar FCLF8519P3BNL-IG
B7: 4 x 10 Gb SR SFP+ transceivers Finisar FCLF8574D3BCL-IG
B8: Use these transceivers with the network packet capture card, labeled as [5] in the appliance diagram.
A9: Network management transceivers | B9: Lenovo Dual Rate 10G/25G SFP28 Transceiver,
B10: The transceivers has the following part numbers: AFBR-735ASMZ-LVX
B11: Use these transceivers with the management ports, labeled as [4] in the appliance diagram
A12: Ports | B12: 4-port 1 GbE TX OCP
B13: 2-port 10/25 GbE SFP28
B14: 4 x Network capture (SFP+) ports
B15: 1 x 1 GbE RJ-45 Ethernet systems management IPMI (XCC) port
A16: Storage | B16: 480 GB: 2 x 480 GB 2.5” SSD RAID 1
B17: Controller: RAID 540-8i
A18: Memory | B18: 256 GB (8 x 32 GB)
A19: Traffic | B19: 10 Gbps
A20: Power supply | B20: Dual redundant 1100 W AC power supply
A21: Dimensions | B21: 30.1 inches deep x 17.5 inches wide x 3.4 inches high
A22: Note:
A23: NBAD is appliance based tap/span/port mirroring done by IBM hardware which is known as QNI. and it typically requires Throughput information from Point of capture (such as router, switches, firewall) to identify North-South and/or East-West (vice versa) packet traffic and is converted to qflow and sent to Flow processor. Since we do not have throughput information right now, we can take 10 Gbps as ball park and suggest 1920 QNI Appliance.
A27: PIM users - 50
A28: Description | B28: PAM Application Server(User will connect to PAM Server to access any devices) | C28: PAM Database Server (Privilege credentials will be stored in database in encrypted manner) | D28: PAM Distributed engine(optional)
A29: No of VM | B29: 3(considering HA + DR) | C29: 3(Considering HA + DR) | D29: 3(Considering HA + DR)
A30: Operating System | B30: Windows Server | C30: Windows Server | D30: Windows
A31: VCPU | B31: 8 | C31: 8 | D31: 4
A32: RAM | B32: 16 | C32: 16 | D32: 8
A33: HDD | B33: 500 | C33: 300 | D33: 200
A34: Required Component | B34: IIS | C34: Microsoft SQL Standard Database
B36: DC | C36: DR
B37: =16+16+8 -> 40 | C37: =8+8+4 -> 20 | D37: =24+24 -> 48
B38: =32+32+16 -> 80 | C38: =16+16+8 -> 40
B39: =1000+600+400 -> 2000 | C39: =500+300+200 -> 1000
A46: EPS - 5000
A48: https://www.ibm.com/docs/en/qsip/7.5?topic=vai-requirements
A49: S.No | B49: Application | C49: Location | D49: Solution Component | E49: VM Qty | F49: HA (Optional) | G49: OS | H49: Peak EPS/FPM | I49: Core | J49: P/VM | K49: RAM | L49: Storage | M49: Virtualization | N49: Remarks
K50: (in GB) | L50: (in TB)
A51: 1 | B51: SIEM | C51: DC | D51: Console | E51: 2 | F51: yes | G51: Included | H51: 30K EPS & 1000K FPM | I51: 40 | J51: V | K51: 128 | L51: 14 | M51: VMWare/Hyperv/KVM
A52: 2 | B52: SIEM | C52: DC | D52: App Host | E52: 2 | F52: Yes | G52: Included | H52: NA | I52: 24 | J52: V | K52: 64 | L52: 3 | M52: VMWare/Hyperv/KVM
A55: S.No | B55: Application | C55: Location | D55: Solution Component | E55: VM Qty | F55: HA (Optional) | G55: OS | H55: Peak EPS/FPM | I55: Core | J55: P/VM | K55: RAM | L55: Storage | M55: Virtualization | N55: Remarks
K56: (in GB) | L56: (in TB)
A57: 1 | B57: SIEM | C57: DR | D57: Console | E57: 2 | F57: yes | G57: Included | H57: 30K EPS & 1000K FPM | I57: 40 | J57: V | K57: 128 | L57: 14 | M57: VMWare/Hyperv/KVM
A58: 2 | B58: SIEM | C58: DR | D58: App Host | E58: 2 | F58: Yes | G58: Included | H58: NA | I58: 24 | J58: V | K58: 64 | L58: 3 | M58: VMWare/Hyperv/KVM
A65: S.No. | B65: Solution | C65: Qty - DC | D65: Type | E65: Virtual CPU - Minimum | F65: Virtual RAM - Minimum | G65: OS & App Storage | H65: HA | I65: Type (Physical / VM) | J65: OS Version | K65: Interface | L65: IoPs | M65: Remarks
A66: 1 | B66: Master Nodes | C66: 3 | D66: Virtual | E66: 16 | F66: 32 | G66: 120 | H66: inbuilt | I66: VM | J66: RHEL CoreOS | K66: Virtual | N66: =E66*C66 -> 48 | O66: =F66*C66 -> 96 | P66: =G66*C66 -> 360
A67: 2 | B67: Worker Nodes - UAX | C67: 3 | D67: Virtual | E67: 16 | F67: 64 | G67: 120 | H67: inbuilt | I67: VM | J67: RHEL CoreOS | K67: Virtual | N67: =E67*C67 -> 48 | O67: =F67*C67 -> 192 | P67: =G67*C67 -> 360
A68: 3 | B68: HAProxy Load Balancer 2 | C68: 2 | D68: Virtual | E68: 4 | F68: 16 | G68: 100 | H68: NA | I68: VM | J68: RHEL | K68: Virtual | M68: Preferable is a physical loadbalancer. | N68: =E68*C68 -> 8 | O68: =F68*C68 -> 32 | P68: =G68*C68 -> 200
A69: 4 | B69: Kubernetes Persistent Storage | C69: 1 | D69: Virtual | G69: 3584 | H69: NA | I69: VM | K69: Virtual | L69: 10 IOPS/GB | M69: https://www.ibm.com/docs/en/cloud-paks/cp-security/1.10?topic=planning-storage-requirements | N69: =E69*C69 -> 0 | O69: =F69*C69 -> 0 | P69: =G69*C69 -> 3584
A70: 5 | B70: Bastion Node | C70: 1 | D70: Virtual | E70: 4 | F70: 16 | G70: 100 | H70: NA | I70: VM | J70: RHEL | K70: Virtual | N70: =E70*C70 -> 4 | O70: =F70*C70 -> 16 | P70: =G70*C70 -> 100
A71: 6 | B71: Edge Gateway | C71: 1 | D71: Virtual | E71: 8 | F71: 32 | G71: 120 | H71: NA | I71: VM | J71: RHEL | K71: Virtual | N71: =E71*C71 -> 8 | O71: =F71*C71 -> 32 | P71: =G71*C71 -> 120
A72: Total | C72: =SUM(C66:C71) -> 11 | D72: =SUM(D66:D71) -> 0 | E72: =SUM(E66:E71) -> 48 | F72: =SUM(F66:F71) -> 160 | G72: =SUM(G66:G71) -> 4144
N73: =SUM(N66:N72) -> 116 | O73: =SUM(O66:O72) -> 368 | P73: =SUM(P66:P72) -> 4724
A77: S.No. | B77: Solution | C77: Qty - DR | D77: Type | E77: Virtual CPU - Minimum | F77: Virtual RAM - Minimum | G77: OS & App Storage | H77: HA | I77: Type (Physical / VM) | J77: OS Version | K77: Interface | L77: IoPs | M77: Remarks
A78: 1 | B78: Master Nodes | C78: 3 | D78: Virtual | E78: 16 | F78: 32 | G78: 120 | H78: inbuilt | I78: VM | J78: RHEL CoreOS | K78: Virtual
A79: 2 | B79: Worker Nodes - UAX | C79: 3 | D79: Virtual | E79: 16 | F79: 64 | G79: 120 | H79: inbuilt | I79: VM | J79: RHEL CoreOS | K79: Virtual
A80: 3 | B80: HAProxy Load Balancer 2 | C80: 2 | D80: Virtual | E80: 4 | F80: 16 | G80: 100 | H80: NA | I80: VM | J80: RHEL | K80: Virtual | M80: Preferable is a physical loadbalancer.
A81: 4 | B81: Kubernetes Persistent Storage | C81: 1 | D81: Virtual | G81: 3584 | H81: NA | I81: VM | K81: Virtual | L81: 10 IOPS/GB | M81: https://www.ibm.com/docs/en/cloud-paks/cp-security/1.10?topic=planning-storage-requirements
A82: 5 | B82: Bastion Node | C82: 1 | D82: Virtual | E82: 4 | F82: 16 | G82: 100 | H82: NA | I82: VM | J82: RHEL | K82: Virtual
A83: 6 | B83: Edge Gateway | C83: 1 | D83: Virtual | E83: 8 | F83: 32 | G83: 120 | H83: NA | I83: VM | J83: RHEL | K83: Virtual
A84: Total | C84: 10 | E84: 116 | F84: 368 | G84: 4724

Sheet BoM Additional
A1: Sr. No. | B1: Infrastructure | C1: Device | D1: Mode | E1: Quantity
A2: 10.1 | B2: Network Components | C2: Router | D2: HA | E2: 2
A3: 10.1 | B3: Network Components | C3: Core Distribution Switch (L3) | D3: HA | E3: 2
A4: 10.1 | B4: Network Components | C4: Low Latency Access Switch (L2) | D4: HA | E4: 2
A5: 10.1 | B5: Network Components | C5: Next Generation Firewall with VPN | D5: HA | E5: 2
A6: 10.1 | B6: Network Components | C6: Load Balancer, WAF | D6: -- | E6: 1
A7: 10.2 | B7: Nutanix HCI Servers | C7: Nodes / Servers with Hypervisor | D7: - | E7: 8
A8: 10.2 | B8: Nutanix HCI Servers | C8: Licence Acropolis Operating System (Files for AOS + Prism) | D8: - | E8: 1+1
A9: 10.2 | B9: Nutanix HCI Servers | C9: Exchange Servers (Maximum 350 users) | D9: - | E9: 1
A10: 10.3 | B10: Storage | C10: Storage Area Network (SAN) | D10: - | E10: 1
A11: 10.3 | B11: Storage | C11: Network Attached Storage (NAS) | D11: - | E11: 3
A12: 10.3 | B12: Storage | C12: Blackbox | D12: - | E12: 1
A13: 10.3 | B13: Storage | C13: Backup Software & Devices | D13: - | E13: 1
A14: 10.4 | B14: Security | C14: Security Information and Event Management (SIEM) | D14: - | E14: 1
A15: 10.4 | B15: Security | C15: Antivirus and Data Leak Protection (DLP) | D15: - | E15: 1
A16: 10.4 | B16: Security | C16: Extended Detection and Response (XDR) | D16: - | E16: 1
A17: 10.4 | B17: Security | C17: Privileged Access Management (PAM) | D17: - | E17: 1
A18: 10.4 | B18: Security | C18: Security Orchestration, Automation & Response (SOAR) | D18: - | E18: 1
A19: 10.4 | B19: Security | C19: Identity & Access Management (IAM/SSO) | D19: - | E19: 1
A20: 10.4 | B20: Security | C20: Threat Intelligence & Compliance Reporting | D20: - | E20: 1
A21: 10.5 | B21: Software & Monitoring | C21: Database Licenses (SQL/Oracle/MySQL) | D21: - | E21: As per sizing
A22: 10.5 | B22: Software & Monitoring | C22: DR Orchestration Tool | D22: - | E22: 1
A23: 10.5 | B23: Software & Monitoring | C23: Monitoring Tools (Infra + Bandwidth + Logs) | D23: - | E23: 1
A24: 10.6 | B24: Managed Services | C24: Manpower for SOC/NOC Operations | D24: - | E24: As per SLA
A25: 10.6 | B25: Managed Services | C25: Annual CERT-In VAPT Service | D25: - | E25: Yearly
A26: 10.6 | B26: Managed Services | C26: DR Drills & SLA Reporting | D26: - | E26: Half-Yearly

Sheet RFP BoM
A1: Sr. No. | B1: Infrastructure | C1: Device | D1: Mode | E1: Quantity
A2: 10.1 | B2: Network Components | C2: Router | D2: HA | E2: 2
A3: 10.1 | B3: Network Components | C3: Core Distribution Switch (L3) | D3: HA | E3: 2
A4: 10.1 | B4: Network Components | C4: Low Latency Access Switch (L2) | D4: HA | E4: 2
A5: 10.1 | B5: Network Components | C5: Next Generation Firewall with VPN | D5: HA | E5: 2
A6: 10.1 | B6: Network Components | C6: Load Balancer, WAF | D6: -- | E6: 1
A7: 10.2 | B7: Nutanix HCI Servers | C7: Nodes / Servers with Hypervisor | D7: - | E7: 8
A8: 10.2 | B8: Nutanix HCI Servers | C8: Licence Acropolis Operating System (Files for AOS + Prism) | D8: - | E8: 1+1
A9: 10.2 | B9: Nutanix HCI Servers | C9: Exchange Servers (Maximum 350 users) | D9: - | E9: 1
A10: 10.3 | B10: Storage | C10: Storage Area Network (SAN) | D10: - | E10: 1
A11: 10.3 | B11: Storage | C11: Network Attached Storage (NAS) | D11: - | E11: 3
A12: 10.3 | B12: Storage | C12: Blackbox | D12: - | E12: 1
A13: 10.4 | B13: Security | C13: Security Information and Event Management (SIEM) | D13: - | E13: 1
A14: 10.4 | B14: Security | C14: Antivirus and Data Leak Protection (DLP) | D14: - | E14: 1
A15: 10.4 | B15: Security | C15: Extended Detection and Response (XDR) | D15: - | E15: 1
A16: 10.4 | B16: Security | C16: Privileged Access Management (PAM) | D16: - | E16: 1

Sheet BID Format
B2: Description | C2: Qty | D2: Unit Price | E2: Total Price | F2: Tax | G2: Total With
G3: Tax
B4: Router (2 Units) | C4: 2 | D4: =Working!J11 -> 502570.41 | E4: =Working!K11 -> 1005140.8 | F4: =E4*18% -> 180925.35 | G4: =SUM(E4:F4) -> 1186066.2
B5: L3 Switch (2 units + line cards) | C5: 2 | D5: =Working!J12 -> 2543903.4 | E5: =Working!K12 -> 5087806.8 | F5: =E5*18% -> 915805.22 | G5: =SUM(E5:F5) -> 6003612
B6: Firewalls (2 units) | C6: 2 | D6: =Working!J10 -> 1435000 | E6: =Working!K10 -> 2870000 | F6: =E6*18% -> 516600 | G6: =SUM(E6:F6) -> 3386600
B7: Secure VPN for 100 User | C7: 1 | D7: Included in Fiewall | E7: Included in Fiewall | F7: Included in Fiewall | G7: Included in Fiewall
B8: L2 Switch | C8: 2 | D8: =Working!J13 -> 303703.7 | E8: =Working!K13 -> 607407.41 | F8: =E8*18% -> 109333.33 | G8: =SUM(E8:F8) -> 716740.74
B9: Load Balancer and WAF | C9: 1 | D9: =Working!J15 -> 4701333.3 | E9: =Working!K15 -> 4701333.3 | F9: =E9*18% -> 846240 | G9: =SUM(E9:F9) -> 5547573.3
B10: Nutanix HCI Nodes | C10: 8 | D10: =Working!J9 -> 10448726 | E10: =Working!K9 -> 83589811 | F10: =E10*18% -> 15046166 | G10: =SUM(E10:F10) -> 98635978
B11: Unified Storage (SAN, NAS & Object) | C11: 1 | D11: =Working!J16 -> 29647468 | E11: =Working!K16 -> 29647468 | F11: =E11*18% -> 5336544.2 | G11: =SUM(E11:F11) -> 34984012
B12: NAS Devices | C12: 3 | D12: =Working!J18 -> 607407.41 | E12: =Working!K18 -> 1822222.2 | F12: =E12*18% -> 328000 | G12: =SUM(E12:F12) -> 2150222.2
B13: DLP (60 users) | C13: 1 | D13: =Working!J38 -> 22222.222 | E13: =Working!K38 -> 1111111.1 | F13: =E13*18% -> 200000 | G13: =SUM(E13:F13) -> 1311111.1
B14: Linux Licenses (17) + Database (3) as mentioned in License details | C14: 1 | D14: =SUM(Working!J29:J31) -> 790580.31 | E14: =SUM(Working!K29:K31) -> 7082335.1 | F14: =E14*18% -> 1274820.3 | G14: =SUM(E14:F14) -> 8357155.4
B15: Windows Licenses (13) + Database (12) ) as mentioned in License details | C15: 1 | D15: =SUM(Working!J26,Working!J28) -> 998498.15 | E15: =SUM(Working!K26,Working!K28) -> 16515797 | F15: =E15*18% -> 2972843.4 | G15: =SUM(E15:F15) -> 19488640
B16: XDR (65 endpoints) | C16: 1 | D16: =Working!J37 -> 1185185.2 | E16: =Working!K37 -> 1185185.2 | F16: =E16*18% -> 213333.33 | G16: =SUM(E16:F16) -> 1398518.5
B17: Blackbox Storage | C17: 1 | D17: =Working!J17 -> 516296.3 | E17: =Working!K17 -> 516296.3 | F17: =E17*18% -> 92933.333 | G17: =SUM(E17:F17) -> 609229.63
B18: SOAR + SIEM wih 1000 EPS for 3 yrs | C18: 1 | D18: =Working!J36 -> 14621601 | E18: =Working!K36 -> 14621601 | F18: =E18*18% -> 2631888.2 | G18: =SUM(E18:F18) -> 17253490
B19: Intel Fortran (6 Licenses) | C19: 1 | D19: As per prebid meeting not require | E19: As per prebid meeting not require | F19: As per prebid meeting not require | G19: As per prebid meeting not require
B20: GitLab Premium (10 users) | C20: 1 | D20: =Working!J45 -> 143500 | E20: =Working!K45 -> 1435000 | F20: =E20*18% -> 258300 | G20: =SUM(E20:F20) -> 1693300
B21: PAM (65 users) | C21: 1 | D21: =SUM(Working!J39:J40) -> 206222.22 | E21: =SUM(Working!K39:K40) -> 4871111.1 | F21: =E21*18% -> 876800 | G21: =SUM(E21:F21) -> 5747911.1
B22: Exchange Server (300 users) | C22: 1 | D22: =Working!J27 -> 908155.93 | E22: =Working!K27 -> 1816311.9 | F22: =E22*18% -> 326936.13 | G22: =SUM(E22:F22) -> 2143248
B23: Implementation & Setup Charges (Onetime) | E23: =Working!K19 -> 2469135.8 | F23: =E23*18% -> 444444.44 | G23: =SUM(E23:F23) -> 2913580.2
B24: Migration of Resources charges from DC to DR (OneTime) | E24: =Working!K32 -> 11851852 | F24: =E24*18% -> 2133333.3 | G24: =SUM(E24:F24) -> 13985185
B25: Cloud DC & DR, Connectivity Services (P2P/Lease Line etc) 50 Mbps | D25: ='Broadband Cost'!F5 -> 1440000 | E25: =D25 -> 1440000 | F25: =E25*18% -> 259200 | G25: =SUM(E25:F25) -> 1699200
A26: 5 yr | B26: Managed Support Services (03 Mandatory+02Years Extendable) Lenovo + Nutanix | C26: 1 | D26: =Working!K33+Working!K34 -> 23663985 | E26: =SUM(Working!K33:K34) -> 23663985 | F26: =E26*18% -> 4259517.4 | G26: =SUM(E26:F26) -> 27923503 | H26: 26 l
A27: 5 yr | B27: Operational Support Services (AC, Power, Physical Security etc) (03 Mandatory+02 Years Extendable) | C27: 1 | D27: =Working!J14 -> 43368889 | E27: =Working!K14 -> 43368889 | F27: =E27*18% -> 7806400 | G27: =SUM(E27:F27) -> 51175289 | H27: 57 l
B28: Other (3yrs Managed services) | C28: 1 | D28: ='Monthly Recurring'!H19 -> 19144228 | E28: ='Monthly Recurring'!H19 -> 19144228 | F28: =E28*18% -> 3445961 | G28: =SUM(E28:F28) -> 22590189
B29: Security Audit VAPT (CERT-IN) | C29: 1 | D29: Client Scope | E29: Client Scope | F29: Client Scope | G29: Client Scope | I29: 240000000
B30: Infra Monitoring system | C30: 1 | D30: =Working!J47 -> 1600000 | E30: =Working!K47 -> 1600000 | F30: =E30*18% -> 288000 | G30: =SUM(E30:F30) -> 1888000 | I30: =I29*6% -> 14400000
B31: Wing FTP server Corporate Set of 3 Lic 2yr Support | C31: 1 | D31: =Working!J43 -> 680141.51 | E31: =Working!K43 -> 680141.51 | F31: =E31*18% -> 122425.47 | G31: =SUM(E31:F31) -> 802566.98 | H31: Additional line item | I31: 30000000
B32: IBM SPSS – AMOS version 28 Perpetual Lic with 3Yr Support | C32: 1 | D32: =Working!J44 -> 1899259.3 | E32: =Working!K44 -> 1899259.3 | F32: =E32*18% -> 341866.67 | G32: =SUM(E32:F32) -> 2241125.9 | H32: Additional line item | I32: =I29+I30+I31 -> 284400000
B33: TOTAL | E33: =SUM(E4:E32) -> 2.8460343e+08 | F33: =SUM(F4:F30) -> 50764325 | G33: =SUM(G4:G30) -> 3.3278835e+08 | I33: =I32*18% -> 51192000
B37: TOTAL | E37: 3.2034815e+08 | F37: 57662667 | G37: 3.7801082e+08
E39: 2.7566832e+08 | F39: 49620297 | G39: 3.2528862e+08

Sheet Working
D2: Finance Cost | E2: 0.05 | F2: =13/12 -> 1.0833333 | G2: =F2*3 -> 3.25
D3: CPC | E3: 0.19 | F3: 12%CPC+2%Contingency
D4: Gross Profit Margin - Hardware | E4: 0.18 | K4: =15/12 -> 1.25
D5: Gross Profit Margin - Software | E5: 0.15
B7: Sr.No. | C7: Product | D7: Discription | E7: Qty | F7: Input Cost One Time + 3Y AMC | G7: Finance Cost | H7: Gross Profit Margin | I7: Discount | J7: Cost Per Unit | K7: TOTAL AMOUNT | L7: Final Amt | M7: With GST | O7: Remarks | Q7: Input Cost | S7: CPC
C8: Type | D8: Appliances | E8: N | J8: A
B9: 1 | C9: Physical Server | D9: 2X Intel Xeon Gold 6542Y 24C 250W 2.9GHz Processor, 24X ThinkSystem 64GB TruDDR5 5600MHz (2Rx4) RDIMM, 1X ThinkSystem 440-16i SAS/SATA PCIe Gen4 12Gb Internal HBA, 1X ThinkSystem 2U 8x2.5" SAS/SATA Backplane, 1X Nutanix Flash Node Config, 8X ThinkSystem 2.5" U.3 7500 PRO 7.68TB Read Intensive NVMe PCIe 4.0 x4 HS SSD, 1X ThinkSystem M.2 NVMe 2-Bay RAID Adapter, 2X ThinkSystem M.2 7450 PRO 960GB Read Intensive NVMe PCIe 4.0 x4 NHS SSD 1X ThinkSystem Broadcom 57416 10GBASE-T 2-port OCP Ethernet Adapter, 2X ThinkSystem Broadcom 57414 10/25GbE SFP28 2-port PCIe Ethernet Adapter, 4X SFP+ SR Transceiver, 2X ThinkSystem 1800W 230V Platinum Hot-Swap Gen2 Power Supply, 2X 2.8m, 10A/100-250V, C13 to C14 Jumper Cord (India), 1X TPM 2.0, 1X Enable IPMI-over-LAN, 1X N+N Redundancy With Over-Subscription, 1X G4 x16/x8/x8 PCIe Riser BLKL for Riser 1 Placement, 1X 3Yr Premier 24x7 4Hr Resp ThinkAgile CN HX650 V3 | E9: 8 | F9: ='Lenovo Quote'!D4 -> 6880868.6 | G9: =(F9*$E$2) -> 344043.43 | H9: =$E$4*F9 -> 1238556.4 | J9: =(SUM(F9:H9)/(1-$E$3))-(I9*(SUM(F9:H9)/(1-$E$3))) -> 10448726 | K9: =(J9*E9)-(I9*(J9*E9)) -> 83589811 | M9: =J9*12% -> 1253847.2 | N9: =M9*E9 -> 10030777 | O9: =(SUM(F9:H9)/(1-$E$3)) -> 10448726 | Q9: =F9*E9 -> 55046949 | S9: =K9*$E$3 -> 15882064 | T9: =SUM(F9:H9) -> 8463468.4 | U9: =T9*E9 -> 67707747 | V9: =K9 -> 83589811 | W9: =V9-U9 -> 15882064 | Y9: 100 | Z9: =(Z11*Y9)/Y11 -> 9617577.7 | AB9: 112 | AC9: =(AC11*AB9)/AB11 -> 9479084.6
B10: 2 | C10: Firewall NGFW | D10: Firewall- SONICWALL NSV 470 TOTALSECURE - ADVANCED EDITION 3YR SONICWALL SAAS 365 DAYS OF ADVANCED REPORTING AND ANALYTICS FOR NSV 470 3YR | E10: 2 | F10: =945000 -> 945000 | G10: =(F10*$E$2) -> 47250 | H10: =$E$4*F10 -> 170100 | J10: =(SUM(F10:H10)/(1-$E$3))-(I10*(SUM(F10:H10)/(1-$E$3))) -> 1435000 | K10: =J10*E10 -> 2870000 | Q10: =F10*E10 -> 1890000 | S10: =K10*$E$3 -> 545300 | Y10: 12
B11: 3 | C11: Router | D11: Router Cisco Catalyst C8200-1N-4T | E11: 2 | F11: =OEM!G155 -> 330961 | G11: =(F11*$E$2) -> 16548.05 | H11: =$E$4*F11 -> 59572.98 | J11: =(SUM(F11:H11)/(1-$E$3))-(I11*(SUM(F11:H11)/(1-$E$3))) -> 502570.41 | K11: =J11*E11 -> 1005140.8 | Q11: =F11*E11 -> 661922 | S11: =K11*$E$3 -> 190976.75 | Y11: 88 | Z11: =SUM(F9:H9) -> 8463468.4 | AB11: 100 | AC11: =Z11 -> 8463468.4
B12: 4 | C12: Switch L3 - | D12: Switch L3 Port 24 Port 10 G | E12: 2 | F12: =OEM!G156 -> 1675253.5 | G12: =(F12*$E$2) -> 83762.673 | H12: =$E$4*F12 -> 301545.62 | J12: =(SUM(F12:H12)/(1-$E$3))-(I12*(SUM(F12:H12)/(1-$E$3))) -> 2543903.4 | K12: =J12*E12 -> 5087806.8 | Q12: =F12*E12 -> 3350506.9 | S12: =K12*$E$3 -> 966683.29
B13: 5 | C13: Switch L2 | D13: Switch L2 Port 24 Port 1G | E13: 2 | F13: =OEM!G157 -> 200000 | G13: =(F13*$E$2) -> 10000 | H13: =$E$4*F13 -> 36000 | J13: =(SUM(F13:H13)/(1-$E$3))-(I13*(SUM(F13:H13)/(1-$E$3))) -> 303703.7 | K13: =J13*E13 -> 607407.41 | Q13: =F13*E13 -> 400000 | S13: =K13*$E$3 -> 115407.41
B14: 6 | D14: Operational Support Services (AC, Power, Physical Security etc) (03 Mandatory+02 Years Extendable) | E14: 1 | F14: =Colo!H11 -> 28560000 | G14: =(F14*$E$2) -> 1428000 | H14: =$E$4*F14 -> 5140800 | J14: =(SUM(F14:H14)/(1-$E$3))-(I14*(SUM(F14:H14)/(1-$E$3))) -> 43368889 | K14: =J14*E14 -> 43368889 | Q14: =F14*E14 -> 28560000 | S14: =K14*$E$3 -> 8240088.9 | Z14: =Z9*12% -> 1154109.3 | AC14: =AC9*12% -> 1137490.2
B15: 7 | C15: WAF | D15: WAF 1 Gbps | E15: 1 | F15: =86000*36 -> 3096000 | G15: =(F15*$E$2) -> 154800 | H15: =$E$4*F15 -> 557280 | J15: =(SUM(F15:H15)/(1-$E$3))-(I15*(SUM(F15:H15)/(1-$E$3))) -> 4701333.3 | K15: =J15*E15 -> 4701333.3 | Q15: =F15*E15 -> 3096000 | S15: =K15*$E$3 -> 893253.33 | Z15: =Z9-Z14 -> 8463468.4 | AC15: =AC9-AC14 -> 8341594.5
B16: 8 | C16: Storage | D16: Storage : Lenovo ThinkSystem DG5200 QLC All Flash Array | E16: 1 | F16: ='Lenovo Quote'!G175 -> 19523942 | G16: =(F16*$E$2) -> 976197.12 | H16: =$E$4*F16 -> 3514309.6 | J16: =(SUM(F16:H16)/(1-$E$3))-(I16*(SUM(F16:H16)/(1-$E$3))) -> 29647468 | K16: =J16*E16 -> 29647468 | Q16: =F16*E16 -> 19523942 | S16: =K16*$E$3 -> 5633018.9
B17: 9 | C17: Blackbox | D17: Blackbox | E17: 1 | F17: 340000 | G17: =(F17*$E$2) -> 17000 | H17: =$E$4*F17 -> 61200 | J17: =(SUM(F17:H17)/(1-$E$3))-(I17*(SUM(F17:H17)/(1-$E$3))) -> 516296.3 | K17: =J17*E17 -> 516296.3 | Q17: =F17*E17 -> 340000 | S17: =K17*$E$3 -> 98096.296
B18: 10 | C18: NAS | D18: NAS Storage - (108TB*3) Price Recived from Comnet price list | E18: 3 | F18: 400000 | G18: =(F18*$E$2) -> 20000 | H18: =$E$4*F18 -> 72000 | J18: =(SUM(F18:H18)/(1-$E$3))-(I18*(SUM(F18:H18)/(1-$E$3))) -> 607407.41 | K18: =J18*E18 -> 1822222.2 | Q18: =F18*E18 -> 1200000 | S18: =K18*$E$3 -> 346222.22
C19: Service | D19: One time Implementation charges | E19: 1 | F19: 2000000 | J19: =(SUM(F19:H19)/(1-$E$3))-(I19*(SUM(F19:H19)/(1-$E$3))) -> 2469135.8 | K19: =J19*E19 -> 2469135.8
B20: Total Hardware Cost | F20: =SUM(F9:F18) -> 61952025 | H20: =SUM(H9:H18) -> 11151365 | J20: =SUM(J9:J18) -> 94075298 | K20: =SUM(K9:K19) -> 1.7568551e+08 | M20: =K20*1.18 -> 2.073089e+08 | N20: =M20-K20 -> 31623392 | Q20: =SUM(Q9:Q18) -> 1.1406932e+08 | S20: =SUM(S9:S18) -> 32911111
B21: Sr.No. | C21: Product | D21: Discription | E21: Qty | F21: Input Cost | G21: Finance Cost | H21: Gross Profit Margin | I21: Discount | J21: Cost Per Unit | K21: TOTAL AMOUNT | M21: With GST
B22: 11 | C22: Software | D22: Acropolis Hypervisor | E22: 1 | F22: Included | J22: Included | K22: Included
B23: 12 | C23: Software | D23: NCI – PRO :- Nutanix Cloud Infrastructure (NCI) Pro Software License - 3Y subscription | E23: 384 | F23: Included | J23: Included | K23: Included
B24: 13 | C24: Software | D24: NCM-Starter :- Nutanix Cloud Manager (NCM) Starter Software License - 3Y subscription | E24: 384 | F24: Included | J24: Included | K24: Included
B25: 14 | C25: Software | D25: NCI-ADR :- Nutanix Cloud Infrastructure (NCI) Advanced Replication (DC 352 + DR 384) - 3Y subscription | E25: 736 | F25: Included | J25: Included | K25: Included
B26: 15 | C26: OS | D26: Win Server Standard Core SLng LSA OLV 16L NL 3Y Aq Y1 AP | E26: =ROUND(('Windows Server'!D33)/16,0) -> 15 | F26: =Redington!E5 -> 154801.75 | G26: =(F26*$E$2) -> 7740.0875 | H26: =$E$5*F26 -> 23220.263 | J26: =(SUM(F26:H26)/(1-$E$3))-(I26*(SUM(F26:H26)/(1-$E$3))) -> 229335.93 | K26: =J26*E26 -> 3440038.9 | M26: =K26*1.18 -> 4059245.9 | N26: =M26-K26 -> 619207 | Q26: =F26*E26 -> 2322026.2 | S26: =K26*$E$3 -> 653607.39
B27: 16 | D27: Exchange Server Ent SLng LSA OLV NL 3Y Aq Y1 AP | E27: 2 | F27: =Redington!E3 -> 613005.25 | G27: =(F27*$E$2) -> 30650.263 | H27: =$E$5*F27 -> 91950.787 | J27: =(SUM(F27:H27)/(1-$E$3))-(I27*(SUM(F27:H27)/(1-$E$3))) -> 908155.93 | K27: =J27*E27 -> 1816311.9 | Q27: =F27*E27 -> 1226010.5 | S27: =K27*$E$3 -> 345099.25
B28: 17 | D28: SQL Server Standard Core SLng LSA OLV 2L NL 3Y Aq Y1 AP | E28: 17 | F28: =Redington!E4 -> 519184.5 | G28: =(F28*$E$2) -> 25959.225 | H28: =$E$5*F28 -> 77877.675 | J28: =(SUM(F28:H28)/(1-$E$3))-(I28*(SUM(F28:H28)/(1-$E$3))) -> 769162.22 | K28: =J28*E28 -> 13075758 | Q28: =F28*E28 -> 8826136.5 | S28: =K28*$E$3 -> 2484394
B29: 18 | C29: OS | D29: Red Hat Enterprise Linux Server for Service Providers, Full Support (Physical or Virtual Nodes, Dedicated, Yearly) 3 year | E29: 10 | F29: =RHEL!D8*3 -> 240546.31 | G29: =(F29*$E$2) -> 12027.315 | H29: =$E$5*F29 -> 36081.946 | J29: =(SUM(F29:H29)/(1-$E$3))-(I29*(SUM(F29:H29)/(1-$E$3))) -> 356364.9 | K29: =J29*E29 -> 3563649 | M29: =K29*1.18 -> 4205105.8 | N29: =M29-K29 -> 641456.82 | Q29: =F29*E29 -> 2405463.1 | S29: =K29*$E$3 -> 677093.31
B30: 19 | D30: Red Hat Enterprise Linux Server for Service Providers, Diagnostic Support (Physical or Virtual Nodes, Dedicated, Yearly) 3 year | E30: 10 | F30: =RHEL!D9*3 -> 200455.26 | G30: =(F30*$E$2) -> 10022.763 | H30: =$E$5*F30 -> 30068.288 | J30: =(SUM(F30:H30)/(1-$E$3))-(I30*(SUM(F30:H30)/(1-$E$3))) -> 296970.75 | K30: =J30*E30 -> 2969707.5 | Q30: =F30*E30 -> 2004552.6 | S30: =K30*$E$3 -> 564244.42
B31: 20 | D31: Red Hat Enterprise Linux, Extended Life Cycle Support Add-On, Layered Support (Physical or Virtual Nodes, Dedicated, Yearly) 3 year | E31: 4 | F31: =RHEL!D10*3 -> 92640.148 | G31: =(F31*$E$2) -> 4632.0074 | H31: =$E$5*F31 -> 13896.022 | J31: =(SUM(F31:H31)/(1-$E$3))-(I31*(SUM(F31:H31)/(1-$E$3))) -> 137244.66 | K31: =J31*E31 -> 548978.65 | Q31: =F31*E31 -> 370560.59 | S31: =K31*$E$3 -> 104305.94
B32: 21 | C32: Service | D32: Migration charges | E32: 1 | F32: 8000000 | G32: =(F32*$E$2) -> 400000 | H32: =$E$5*F32 -> 1200000 | J32: =(SUM(F32:H32)/(1-$E$3))-(I32*(SUM(F32:H32)/(1-$E$3))) -> 11851852 | K32: =J32*E32 -> 11851852 | M32: =K32*1.18 -> 13985185 | N32: =M32-K32 -> 2133333.3 | Q32: =F32*E32 -> 8000000 | S32: =K32*$E$3 -> 2251851.9
B33: 22 | C33: AMC | D33: Extended 2Y HW support & 2Y Nutanix License - HX 650 Node | E33: 8 | F33: ='Lenovo Quote'!D168 -> 1746648.8 | G33: =(F33*$E$2) -> 87332.438 | H33: =$E$5*F33 -> 261997.31 | J33: =(SUM(F33:H33)/(1-$E$3))-(I33*(SUM(F33:H33)/(1-$E$3))) -> 2587627.8 | K33: =J33*E33 -> 20701022 | M33: =K33*1.18 -> 24427206 | N33: =M33-K33 -> 3726184 | Q33: =F33*E33 -> 13973190 | S33: =K33*$E$3 -> 3933194.3
B34: 23 | C34: AMC | D34: Extended 2Y Storage HW support | E34: 1 | F34: ='Lenovo Quote'!D169 -> 2000000 | G34: =(F34*$E$2) -> 100000 | H34: =$E$5*F34 -> 300000 | J34: =(SUM(F34:H34)/(1-$E$3))-(I34*(SUM(F34:H34)/(1-$E$3))) -> 2962963 | K34: =J34*E34 -> 2962963 | M34: =K34*1.18 -> 3496296.3 | N34: =M34-K34 -> 533333.33 | Q34: =F34*E34 -> 2000000 | S34: =K34*$E$3 -> 562962.96
B35: 24 | C35: Service | D35: SIEM DC Qty. 50 and DR 50 | E35: 0 | F35: 0 | G35: =(F35*$E$2) -> 0 | H35: =$E$5*F35 -> 0 | J35: =(SUM(F35:H35)/(1-$E$3))-(I35*(SUM(F35:H35)/(1-$E$3))) -> 0 | K35: =J35*E35 -> 0 | S35: =K35*$E$3 -> 0
B36: 25 | C36: Service | D36: SOAR Qty.3 | E36: 1 | F36: =OEM!E163 -> 9869580.9 | G36: =(F36*$E$2) -> 493479.04 | H36: =$E$5*F36 -> 1480437.1 | J36: =(SUM(F36:H36)/(1-$E$3))-(I36*(SUM(F36:H36)/(1-$E$3))) -> 14621601 | K36: =J36*E36 -> 14621601 | Q36: =F36*E36 -> 9869580.9 | S36: =K36*$E$3 -> 2778104.2
B37: 27 | C37: Service | D37: XDR - 50 VM+ Other Devices 15 EDR included | E37: 1 | F37: =OEM!F170 -> 800000 | G37: =(F37*$E$2) -> 40000 | H37: =$E$5*F37 -> 120000 | J37: =(SUM(F37:H37)/(1-$E$3))-(I37*(SUM(F37:H37)/(1-$E$3))) -> 1185185.2 | K37: =J37*E37 -> 1185185.2 | Q37: =F37*E37 -> 800000 | S37: =K37*$E$3 -> 225185.19
B38: 28 | C38: Service | D38: DLP | E38: 50 | F38: =OEM!E46*3 -> 15000 | G38: =(F38*$E$2) -> 750 | H38: =$E$5*F38 -> 2250 | J38: =(SUM(F38:H38)/(1-$E$3))-(I38*(SUM(F38:H38)/(1-$E$3))) -> 22222.222 | K38: =J38*E38 -> 1111111.1 | Q38: =F38*E38 -> 750000 | S38: =K38*$E$3 -> 211111.11
B39: 29 | C39: Service | D39: PAM Admin User-based License | E39: 5 | F39: =(Cyberdristi!E3)*3 -> 96000 | G39: =(F39*$E$2) -> 4800 | H39: =$E$5*F39 -> 14400 | J39: =(SUM(F39:H39)/(1-$E$3))-(I39*(SUM(F39:H39)/(1-$E$3))) -> 142222.22 | K39: =J39*E39 -> 711111.11 | L39: 50Vm's + 15 network devices | Q39: =F39*E39 -> 480000 | S39: =K39*$E$3 -> 135111.11
B40: 30 | C40: Service | D40: PAM End Device | E40: 65 | F40: =(1200*36) -> 43200 | G40: =(F40*$E$2) -> 2160 | H40: =$E$5*F40 -> 6480 | J40: =(SUM(F40:H40)/(1-$E$3))-(I40*(SUM(F40:H40)/(1-$E$3))) -> 64000 | K40: =J40*E40 -> 4160000 | Q40: =(900*36) -> 32400 | S40: =K40*$E$3 -> 790400
B41: 31 | C41: Service | D41: VAPT - 65 Devices ( Yearly Once as per Call) | E41: 0 | F41: 0 | G41: =(F41*$E$2) -> 0 | H41: =$E$5*F41 -> 0 | J41: =(SUM(F41:H41)/(1-$E$3))-(I41*(SUM(F41:H41)/(1-$E$3))) -> 0 | K41: =J41*E41 -> 0 | S41: =K41*$E$3 -> 0
B42: 32 | C42: Service | D42: VPN | E42: 0 | F42: 0 | G42: =(F42*$E$2) -> 0 | H42: =$E$5*F42 -> 0 | J42: =(SUM(F42:H42)/(1-$E$3))-(I42*(SUM(F42:H42)/(1-$E$3))) -> 0 | K42: =J42*E42 -> 0 | S42: =K42*$E$3 -> 0
B43: 33 | C43: Lic | D43: Wing FTP server Corporate Set of 3 Lic | E43: 1 | F43: 459095.52 | G43: =(F43*$E$2) -> 22954.776 | H43: =$E$5*F43 -> 68864.328 | J43: =(SUM(F43:H43)/(1-$E$3))-(I43*(SUM(F43:H43)/(1-$E$3))) -> 680141.51 | K43: =J43*E43 -> 680141.51 | L43: Additional line item | Q43: =F43*E43 -> 459095.52 | S43: =K43*$E$3 -> 129226.89
B44: 34 | C44: Lic | D44: IBM SPSS – AMOS version 28 with 3Yr Support Perpetual | E44: 1 | F44: 1282000 | G44: =(F44*$E$2) -> 64100 | H44: =$E$5*F44 -> 192300 | J44: =(SUM(F44:H44)/(1-$E$3))-(I44*(SUM(F44:H44)/(1-$E$3))) -> 1899259.3 | K44: =J44*E44 -> 1899259.3 | L44: Additional line item | Q44: =F44*E44 -> 1282000 | S44: =K44*$E$3 -> 360859.26
B45: 35 | C45: Service | D45: GitLab Self Managed Premium License | E45: 10 | F45: =3*31500 -> 94500 | G45: =(F45*$E$2) -> 4725 | H45: =F45*$E$4 -> 17010 | J45: =(SUM(F45:H45)/(1-$E$3))-(I45*(SUM(F45:H45)/(1-$E$3))) -> 143500 | K45: =J45*E45 -> 1435000 | Q45: =F45*E45 -> 945000 | S45: =K45*$E$3 -> 272650
B46: 36 | C46: Service | D46: Fortran / Intel OneAPI / HPC Tool Kit | E46: 6 | G46: =(F46*$E$2) -> 0 | H46: =$E$5*F46 -> 0 | J46: =(SUM(F46:H46)/(1-$E$3))-(I46*(SUM(F46:H46)/(1-$E$3))) -> 0 | K46: =J46*E46 -> 0 | Q46: =F46*E46 -> 0 | S46: =K46*$E$3 -> 0
B47: 37 | C47: Software | D47: Monitoring Software - eNlight 360 | E47: 1 | F47: =(1000*36)*30 -> 1080000 | G47: =(F47*$E$2) -> 54000 | H47: =$E$5*F47 -> 162000 | J47: =(SUM(F47:H47)/(1-$E$3))-(I47*(SUM(F47:H47)/(1-$E$3))) -> 1600000 | K47: =J47*E47 -> 1600000 | Q47: =(387*36)*65 -> 905580 | S47: =K47*$E$3 -> 304000
B48: Total Software and Services Cost | F48: =SUM(F22:F47) -> 27306658 | J48: =SUM(J22:J47) -> 40457809 | K48: =SUM(K22:K47) -> 88333690 | M48: =K48*1.18 -> 1.0423375e+08 | N48: =M48-K48 -> 15900064 | Q48: =SUM(Q22:Q47) -> 56651596 | S48: =SUM(S26:S47) -> 16783401
J52: without CPC | K52: =K20+K48 -> 2.640192e+08
E53: 2.5413028e+08 | J53: with CPC | K53: =(K52/(1-0.12))+'Monthly Recurring'!H19 -> 3.1916605e+08
E54: 2.2481128e+08 | K54: =K53-K52 -> 55146846
E55: =E53-E54 -> 29318994 | K55: =K53*12% -> 38299926

Sheet Monthly Recurring
K1: 53.612318 | L1: 53.612318 | M1: 1.27 | O1: 1.27
B2: ESDS eNlight Cloud Hosting Services - Datacenter Site | K2: Compute
K3: 162 | L3: 162 | M3: 3 | O3: ='[76]Discount Sheet'!H7 -> 1.01 | P3: NA | Q3: NA
C4: Hosting Components | K4: vCores | L4: RAM | M4: HDD | N4: IOPs | O4: IOPS | P4: OS | Q4: DB
B5: A.1 | C5: eNlight Cloud Hosting | D5: Unit | E5: Cost/Unit | F5: Discount (%) | G5: Discount Unit Rate | H5: MRC | I5: OTC | K5: No | L5: GB | M5: GB | O5: per GB | S5: Input Price
B6: Infra Mgmt Server | C6: =CONCATENATE("vCores ",K6," | RAM ",L6," GB |Performance Disk (1000 IOPs/TB) ",M6," GB | OS ",P6," | DB ",Q6,"") -> vCores 8 | RAM 16 GB |Performance Disk (1000 IOPs/TB) 500 GB | OS Ubuntu | DB NA | D6: 10 | E6: =((K6*$K$3)+(L6*$L$3)+((O6/1000)*$O$3)*M6+M6*$M$3) -> 5640.5 | F6: 10 | G6: =(E6-(E6*F6%)) -> 5076.45 | H6: =D6*G6 -> 50764.5 | I6: 0 | K6: 8 | L6: 16 | M6: 500 | N6: 1 | O6: =M6*N6 -> 500 | P6: Ubuntu | Q6: NA | S6: =T6*D6 -> 25566.956 | T6: =SUMPRODUCT(K6:M6,K1:M1)+SUMPRODUCT(O6,O1) -> 2556.6956
B7: A.2 | C7: Security Services | D7: Unit | E7: Cost/Unit | F7: Discount (%) | G7: Discount Unit Rate | H7: MRC | I7: OTC
B8: Services | C8: Unmetered Internet Bandwidth - Speed Based | D8: 10 | E8: 815 | F8: 15 | G8: =(E8-(E8*F8%)) -> 692.75 | H8: =D8*G8 -> 6927.5 | I8: 0 | S8: =T8*D8 -> 2700 | T8: 270
B9: Services | C9: IPv4- Public IP - Internal Network | D9: 10 | E9: 1566 | F9: 15 | G9: =(E9-(E9*F9%)) -> 1331.1 | H9: =D9*G9 -> 13311 | I9: 0 | S9: =T9*D9 -> 5192.3077 | T9: 519.23077
B10: A.3 | C10: Managed Hosting Services | D10: Unit | E10: Cost/Unit | F10: Discount (%) | G10: Discount Unit Rate | H10: MRC | I10: OTC
B11: Connectivity | C11: Replication link - P2P On prem to Mumbai DC | D11: 50 | E11: Included | F11: Included | G11: Included | H11: Included | T11: 66 | U11: =T11*D11 -> 3300
B12: Services | C12: DR Drill - 2 Per Year- Each DR Drill will be done either for one Application / number of application, separate DR Drill for One Application will not be done, and if the separate DR drill will be require then additional charges for each DR Drill will be applicable. | D12: 0 | E12: 10555 | G12: =(E12-(E12*F12%)) -> 10555 | H12: =D12*G12 -> 0 | I12: 0 | S12: =T12*D12 -> 0 | T12: 3500
B13: Services | C13: Managed Services (OS, db, Storage, Firewall, Replication, Antivirus, EDR, XDR, SIEM, SOAR) | D13: 1 | E13: =SUM(H21:H27) -> 511979 | F13: 10 | G13: =(E13-(E13*F13%)) -> 460781.1 | H13: =D13*G13 -> 460781.1 | I13: 0 | S13: =SUM(S21:S27) -> 163076.9
B14: No. | C14: DESCRIPTION | H14: MRC | I14: OTC
B15: 1 | C15: Infrastructure (A.1 + A.2) | H15: =SUM(H6:H9) -> 71003 | I15: =SUM(I6:I8) -> 0
B16: 2 | C16: Managed Services (A.4) | H16: =SUM(H11:H13) -> 460781.1 | S16: =SUM(S6:S14) -> 196536.16 | U16: =SUM(U11:U15) -> 3300
C17: Total Monthly Service Pay Without Taxes (A.1 + A.2 + A.3 + A.4) | H17: =SUM(H15:H16) -> 531784.1 | S17: =S16*36 -> 7075301.9
H19: =36*H17 -> 19144228
B21: Services | C21: Operating System Management Services - (Windows + Linux server) | D21: 50 | E21: 1500 | G21: =(E21-(E21*F21%)) -> 1500 | H21: =D21*G21 -> 75000 | I21: 0 | S21: =T21*D21 -> 29000 | T21: 580
B22: Services | C22: Database - Managed Services (MSSQL Std Edition) | D22: 7 | E22: 7500 | G22: =(E22-(E22*F22%)) -> 7500 | H22: =D22*G22 -> 52500 | I22: 0 | S22: =T22*D22 -> 19093.685 | T22: =272.766932379189*10 -> 2727.6693
B23: Services | C23: Storage Management Services per TB | D23: 450 | E23: 755 | F23: 10 | G23: =(E23-(E23*F23%)) -> 679.5 | H23: =D23*G23 -> 305775 | I23: 0 | S23: =T23*D23 -> 96650.205 | T23: 214.77823
B24: Services | C24: Firewall Management Services | D24: 2 | E24: 11547 | G24: =(E24-(E24*F24%)) -> 11547 | H24: =D24*G24 -> 23094 | I24: 0 | S24: =T24*D24 -> 6565.3516 | T24: 3282.6758
B25: Services | C25: Replication Managemnt & Monitoring | D25: 2 | E25: 1500 | G25: =(E25-(E25*F25%)) -> 1500 | H25: =D25*G25 -> 3000 | I25: 0 | S25: =T25*D25 -> 519.75701 | T25: 259.8785
B26: Sevice | C26: SIEM+SOAR management | D26: 50 | E26: 700 | F26: 10 | G26: =(E26-(E26*F26%)) -> 630 | H26: =D26*G26 -> 31500 | I26: 0 | S26: =T26*D26 -> 4247.9017 | T26: 84.958033
B27: Services | C27: DR Drill - 2 Per Year- Each DR Drill will be done either for one Application / number of application, separate DR Drill for One Application will not be done, and if the separate DR drill will be require then additional charges for each DR Drill will be applicable. | D27: 2 | E27: 10555 | G27: 10555 | H27: =D27*G27 -> 21110 | I27: 0 | S27: =T27*D27 -> 7000 | T27: 3500

Sheet Working Service
D2: Finance Cost | E2: 0.05
D3: CPC | E3: 0.12
D4: Gross Profit Margin - Hardware | E4: 0.18 | J4: =15/12 -> 1.25
D5: Gross Profit Margin - Software | E5: 0.15
B7: Sr.No. | C7: Product | D7: Discription | E7: Qty | F7: Input Cost One Time + 3Y AMC | G7: Finance Cost | H7: Gross Profit Margin | I7: Cost Per Unit | J7: TOTAL AMOUNT | K7: Final Amt | L7: With GST | N7: Remarks | P7: Input Cost | R7: CPC
C8: Type | D8: Appliances | E8: N | I8: A
B9: 1 | C9: Physical Server | D9: 2X Intel Xeon Gold 6542Y 24C 250W 2.9GHz Processor, 24X ThinkSystem 64GB TruDDR5 5600MHz (2Rx4) RDIMM, 1X ThinkSystem 440-16i SAS/SATA PCIe Gen4 12Gb Internal HBA, 1X ThinkSystem 2U 8x2.5" SAS/SATA Backplane, 1X Nutanix Flash Node Config, 8X ThinkSystem 2.5" U.3 7500 PRO 7.68TB Read Intensive NVMe PCIe 4.0 x4 HS SSD, 1X ThinkSystem M.2 NVMe 2-Bay RAID Adapter, 2X ThinkSystem M.2 7450 PRO 960GB Read Intensive NVMe PCIe 4.0 x4 NHS SSD 1X ThinkSystem Broadcom 57416 10GBASE-T 2-port OCP Ethernet Adapter, 2X ThinkSystem Broadcom 57414 10/25GbE SFP28 2-port PCIe Ethernet Adapter, 4X SFP+ SR Transceiver, 2X ThinkSystem 1800W 230V Platinum Hot-Swap Gen2 Power Supply, 2X 2.8m, 10A/100-250V, C13 to C14 Jumper Cord (India), 1X TPM 2.0, 1X Enable IPMI-over-LAN, 1X N+N Redundancy With Over-Subscription, 1X G4 x16/x8/x8 PCIe Riser BLKL for Riser 1 Placement, 1X 3Yr Premier 24x7 4Hr Resp ThinkAgile CN HX650 V3 | E9: 8 | F9: ='Lenovo Quote'!D4 -> 6880868.6 | G9: =(F9*$E$2) -> 344043.43 | H9: =$E$4*F9 -> 1238556.4 | I9: =+(SUM(F9:H9)/(1-$E$3)) -> 9617577.7 | J9: =I9*E9 -> 76940622 | L9: =I9*12% -> 1154109.3 | M9: =L9*E9 -> 9232874.6 | N9: =(SUM(F9:H9)/(1-$E$3)) -> 9617577.7 | P9: =F9*E9 -> 55046949 | R9: =J9*$E$3 -> 9232874.6 | S9: =SUM(F9:H9) -> 8463468.4 | T9: =S9*E9 -> 67707747 | U9: =J9 -> 76940622 | V9: =U9-T9 -> 9232874.6 | X9: 100 | Y9: =(Y11*X9)/X11 -> 9617577.7 | AA9: 112 | AB9: =(AB11*AA9)/AA11 -> 9479084.6
B10: 2 | C10: Firewall NGFW | D10: Firewall- SONICWALL NSV 470 TOTALSECURE - ADVANCED EDITION 3YR SONICWALL SAAS 365 DAYS OF ADVANCED REPORTING AND ANALYTICS FOR NSV 470 3YR | E10: 2 | F10: 1400000 | G10: =(F10*$E$2) -> 70000 | H10: =$E$4*F10 -> 252000 | I10: =+(SUM(F10:H10)/(1-$E$3)) -> 1956818.2 | J10: =I10*E10 -> 3913636.4 | P10: =F10*E10 -> 2800000 | R10: =J10*$E$3 -> 469636.36 | X10: 12
B11: 3 | C11: Router | D11: Router Cisco Catalyst C8200-1N-4T | E11: 2 | F11: 600000 | G11: =(F11*$E$2) -> 30000 | H11: =$E$4*F11 -> 108000 | I11: =+(SUM(F11:H11)/(1-$E$3)) -> 838636.36 | J11: =I11*E11 -> 1677272.7 | P11: =F11*E11 -> 1200000 | R11: =J11*$E$3 -> 201272.73 | X11: 88 | Y11: =SUM(F9:H9) -> 8463468.4 | AA11: 100 | AB11: =Y11 -> 8463468.4
B12: 4 | C12: Switch L3 - | D12: Switch L3 Port 24 Port 10 G | E12: 2 | F12: 1000000 | G12: =(F12*$E$2) -> 50000 | H12: =$E$4*F12 -> 180000 | I12: =+(SUM(F12:H12)/(1-$E$3)) -> 1397727.3 | J12: =I12*E12 -> 2795454.5 | P12: =F12*E12 -> 2000000 | R12: =J12*$E$3 -> 335454.55
B13: 5 | C13: Switch L2 | D13: Switch L2 Port 24 Port 1G | E13: 2 | F13: 800000 | G13: =(F13*$E$2) -> 40000 | H13: =$E$4*F13 -> 144000 | I13: =+(SUM(F13:H13)/(1-$E$3)) -> 1118181.8 | J13: =I13*E13 -> 2236363.6 | P13: =F13*E13 -> 1600000 | R13: =J13*$E$3 -> 268363.64
B14: 6 | D14: Operational Support Services (AC, Power, Physical Security etc) (03 Mandatory+02 Years Extendable) | E14: 2 | F14: =Colo!F10 -> 1163000 | G14: =(F14*$E$2) -> 58150 | H14: =$E$4*F14 -> 209340 | I14: =+(SUM(F14:H14)/(1-$E$3)) -> 1625556.8 | J14: =I14*E14 -> 3251113.6 | P14: =F14*E14 -> 2326000 | R14: =J14*$E$3 -> 390133.64 | Y14: =Y9*12% -> 1154109.3 | AB14: =AB9*12% -> 1137490.2
B15: 7 | C15: WAF | D15: WAF 1 Gbps | E15: 1 | F15: =68825*36 -> 2477700 | G15: =(F15*$E$2) -> 123885 | H15: =$E$4*F15 -> 445986 | I15: =+(SUM(F15:H15)/(1-$E$3)) -> 3463148.9 | J15: =I15*E15 -> 3463148.9 | P15: =F15*E15 -> 2477700 | R15: =J15*$E$3 -> 415577.86 | Y15: =Y9-Y14 -> 8463468.4 | AB15: =AB9-AB14 -> 8341594.5
B16: 8 | C16: Storage | D16: Storage : Lenovo ThinkSystem DG5200 QLC All Flash Array | E16: 1 | F16: ='Lenovo Quote'!E117 -> 32768967 | G16: =(F16*$E$2) -> 1638448.3 | H16: =$E$4*F16 -> 5898414.1 | I16: =+(SUM(F16:H16)/(1-$E$3)) -> 45802079 | J16: =I16*E16 -> 45802079 | P16: =F16*E16 -> 32768967 | R16: =J16*$E$3 -> 5496249.5
B17: 9 | C17: Blackbox | D17: Blackbox | E17: 1 | F17: 340000 | G17: =(F17*$E$2) -> 17000 | H17: =$E$4*F17 -> 61200 | I17: =+(SUM(F17:H17)/(1-$E$3)) -> 475227.27 | J17: =I17*E17 -> 475227.27 | P17: =F17*E17 -> 340000 | R17: =J17*$E$3 -> 57027.273
B18: 10 | C18: NAS | D18: NAS Storage - (108TB*3) | E18: 3 | F18: 2000000 | G18: =(F18*$E$2) -> 100000 | H18: =$E$4*F18 -> 360000 | I18: =+(SUM(F18:H18)/(1-$E$3)) -> 2795454.5 | J18: =I18*E18 -> 8386363.6 | P18: =F18*E18 -> 6000000 | R18: =J18*$E$3 -> 1006363.6
C19: Service | D19: One time Implementation charges | E19: 1 | F19: 2000000 | G19: =(F19*$E$2) -> 100000 | H19: =$E$4*F19 -> 360000 | I19: =+(SUM(F19:H19)/(1-$E$3)) -> 2795454.5 | J19: =I19*E19 -> 2795454.5
B20: Total Hardware Cost | F20: =SUM(F9:F18) -> 49430536 | H20: =SUM(H9:H18) -> 8897496.4 | I20: =SUM(I9:I18) -> 69090408 | J20: =SUM(J9:J19) -> 1.5173674e+08 | L20: =J20*1.18 -> 1.7904935e+08 | M20: =L20-J20 -> 27312612 | P20: =SUM(P9:P18) -> 1.0655962e+08 | R20: =SUM(R9:R18) -> 17872954
B21: Sr.No. | C21: Product | D21: Discription | E21: Qty | F21: Input Cost | G21: Finance Cost | H21: Gross Profit Margin | I21: Cost Per Unit | J21: TOTAL AMOUNT | L21: With GST
B22: 11 | C22: Software | D22: Acropolis Hypervisor | E22: 1 | F22: Included | I22: Included | J22: Included
B23: 12 | C23: Software | D23: NCI – PRO :- Nutanix Cloud Infrastructure (NCI) Pro Software License - 3Y subscription | E23: 384 | F23: Included | I23: Included | J23: Included
B24: 13 | C24: Software | D24: NCM-Starter :- Nutanix Cloud Manager (NCM) Starter Software License - 3Y subscription | E24: 384 | F24: Included | I24: Included | J24: Included
B25: 14 | C25: Software | D25: NCI-ADR :- Nutanix Cloud Infrastructure (NCI) Advanced Replication (DC 352 + DR 384) - 3Y subscription | E25: 736 | F25: Included | I25: Included | J25: Included
B26: 15 | C26: OS | D26: Win Server Standard Core SLng LSA OLV 16L NL 3Y Aq Y1 AP | E26: =ROUND(('Windows Server'!D33)/16,0) -> 15 | F26: =Redington!E5 -> 154801.75 | G26: =(F26*$E$2) -> 7740.0875 | H26: =$E$5*F26 -> 23220.263 | I26: =+(SUM(F26:H26)/(1-$E$3)) -> 211093.3 | J26: =I26*E26 -> 3166399.4 | L26: =J26*1.18 -> 3736351.3 | M26: =L26-J26 -> 569951.9 | P26: =F26*E26 -> 2322026.2 | R26: =J26*$E$3 -> 379967.93
B27: 16 | D27: Exchange Server Ent SLng LSA OLV NL 3Y Aq Y1 AP | E27: 2 | F27: =Redington!E3 -> 613005.25 | G27: =(F27*$E$2) -> 30650.263 | H27: =$E$5*F27 -> 91950.787 | I27: =+(SUM(F27:H27)/(1-$E$3)) -> 835916.25 | J27: =I27*E27 -> 1671832.5 | P27: =F27*E27 -> 1226010.5 | R27: =J27*$E$3 -> 200619.9
B28: 17 | D28: SQL Server Standard Core SLng LSA OLV 2L NL 3Y Aq Y1 AP | E28: 17 | F28: =Redington!E4 -> 519184.5 | G28: =(F28*$E$2) -> 25959.225 | H28: =$E$5*F28 -> 77877.675 | I28: =+(SUM(F28:H28)/(1-$E$3)) -> 707978.86 | J28: =I28*E28 -> 12035641 | P28: =F28*E28 -> 8826136.5 | R28: =J28*$E$3 -> 1444276.9
B29: 18 | C29: OS | D29: Red Hat Enterprise Linux Server for Service Providers, Full Support (Physical or Virtual Nodes, Dedicated, Yearly) 1st year | E29: 10 | F29: =RHEL!D8*3 -> 240546.31 | G29: =(F29*$E$2) -> 12027.315 | H29: =$E$5*F29 -> 36081.946 | I29: =+(SUM(F29:H29)/(1-$E$3)) -> 328017.69 | J29: =I29*E29 -> 3280176.9 | L29: =J29*1.18 -> 3870608.7 | M29: =L29-J29 -> 590431.84 | P29: =F29*E29 -> 2405463.1 | R29: =J29*$E$3 -> 393621.23
B30: 19 | D30: Red Hat Enterprise Linux Server for Service Providers, Diagnostic Support (Physical or Virtual Nodes, Dedicated, Yearly) 1st year | E30: 10 | F30: =RHEL!D9*3 -> 200455.26 | G30: =(F30*$E$2) -> 10022.763 | H30: =$E$5*F30 -> 30068.288 | I30: =+(SUM(F30:H30)/(1-$E$3)) -> 273348.07 | J30: =I30*E30 -> 2733480.7 | P30: =F30*E30 -> 2004552.6 | R30: =J30*$E$3 -> 328017.69
B31: 20 | D31: Red Hat Enterprise Linux, Extended Life Cycle Support Add-On, Layered Support (Physical or Virtual Nodes, Dedicated, Yearly) 1st year | E31: 4 | F31: =RHEL!D10*3 -> 92640.148 | G31: =(F31*$E$2) -> 4632.0074 | H31: =$E$5*F31 -> 13896.022 | I31: =+(SUM(F31:H31)/(1-$E$3)) -> 126327.47 | J31: =I31*E31 -> 505309.9 | P31: =F31*E31 -> 370560.59 | R31: =J31*$E$3 -> 60637.188
B32: 21 | C32: Service | D32: Migration charges | E32: 1 | F32: 9500000 | G32: =(F32*$E$2) -> 475000 | H32: =$E$5*F32 -> 1425000 | I32: =+(SUM(F32:H32)/(1-$E$3)) -> 12954545 | J32: =I32*E32 -> 12954545 | L32: =J32*1.18 -> 15286364 | M32: =L32-J32 -> 2331818.2 | P32: =F32*E32 -> 9500000 | R32: =J32*$E$3 -> 1554545.5
B33: 22 | C33: AMC | D33: Extended 2Y HW support & 2Y Nutanix License - HX 650 Node | E33: 8 | F33: ='Lenovo Quote'!D168 -> 1746648.8 | G33: =(F33*$E$2) -> 87332.438 | H33: =$E$5*F33 -> 261997.31 | I33: =+(SUM(F33:H33)/(1-$E$3)) -> 2381793.8 | J33: =I33*E33 -> 19054350 | L33: =J33*1.18 -> 22484133 | M33: =L33-J33 -> 3429783 | P33: =F33*E33 -> 13973190 | R33: =J33*$E$3 -> 2286522
B34: 23 | C34: AMC | D34: Extended 2Y Storage HW support | E34: 1 | F34: ='Lenovo Quote'!D169 -> 2000000 | G34: =(F34*$E$2) -> 100000 | H34: =$E$5*F34 -> 300000 | I34: =+(SUM(F34:H34)/(1-$E$3)) -> 2727272.7 | J34: =I34*E34 -> 2727272.7 | L34: =J34*1.18 -> 3218181.8 | M34: =L34-J34 -> 490909.09 | P34: =F34*E34 -> 2000000 | R34: =J34*$E$3 -> 327272.73
B35: 24 | C35: Service | D35: SIEM DC Qty. 50 and DR 50 | E35: 1 | F35: =(19000*3)*100 -> 5700000 | G35: =(F35*$E$2) -> 285000 | H35: =$E$5*F35 -> 855000 | I35: =+(SUM(F35:H35)/(1-$E$3)) -> 7772727.3 | J35: =I35*E35 -> 7772727.3 | P35: =(16000*3)*100 -> 4800000 | R35: =J35*$E$3 -> 932727.27
B36: 25 | C36: Service | D36: SOAR Qty.3 | E36: 1 | F36: =4742000*3 -> 14226000 | G36: =(F36*$E$2) -> 711300 | H36: =$E$5*F36 -> 2133900 | I36: =+(SUM(F36:H36)/(1-$E$3)) -> 19399091 | J36: =I36*E36 -> 19399091 | P36: =F36*E36 -> 14226000 | R36: =J36*$E$3 -> 2327890.9
B37: 26 | C37: Service | D37: EDR -50 VM | E37: 1 | F37: =(415*36)*50 -> 747000 | G37: =(F37*$E$2) -> 37350 | H37: =$E$5*F37 -> 112050 | I37: =+(SUM(F37:H37)/(1-$E$3)) -> 1018636.4 | J37: =I37*E37 -> 1018636.4 | P37: =(1200*36)*50 -> 2160000 | R37: =J37*$E$3 -> 122236.36
B38: 27 | C38: Service | D38: XDR - 50 VM+ Other Devices 15 | E38: 1 | F38: =(1400*36)*65 -> 3276000 | G38: =(F38*$E$2) -> 163800 | H38: =$E$5*F38 -> 491400 | I38: =(SUM(F38:H38)/(1-$E$3)) -> 4467272.7 | J38: =I38*E38 -> 4467272.7 | P38: =F38*E38 -> 3276000 | R38: =J38*$E$3 -> 536072.73
B39: 28 | C39: Service | D39: DLP | E39: 50 | F39: =415*36 -> 14940 | G39: =(F39*$E$2) -> 747 | H39: =$E$5*F39 -> 2241 | I39: =+(SUM(F39:H39)/(1-$E$3)) -> 20372.727 | J39: =I39*E39 -> 1018636.4 | P39: =F39*E39 -> 747000 | R39: =J39*$E$3 -> 122236.36
B40: 29 | C40: Service | D40: PAM Admin User-based License | E40: 5 | F40: =(Cyberdristi!E3)*3 -> 96000 | G40: =(F40*$E$2) -> 4800 | H40: =$E$5*F40 -> 14400 | I40: =+(SUM(F40:H40)/(1-$E$3)) -> 130909.09 | J40: =I40*E40 -> 654545.45 | P40: =F40*E40 -> 480000 | R40: =J40*$E$3 -> 78545.455
B41: 30 | C41: Service | D41: PAM End Device | E41: 65 | F41: =(1200*36) -> 43200 | G41: =(F41*$E$2) -> 2160 | H41: =$E$5*F41 -> 6480 | I41: =+(SUM(F41:H41)/(1-$E$3)) -> 58909.091 | J41: =I41*E41 -> 3829090.9 | P41: =(900*36) -> 32400 | R41: =J41*$E$3 -> 459490.91
B42: 31 | C42: Service | D42: VAPT - 65 Devices ( Yearly Once as per Call) | E42: 1 | F42: =(5000*65)*3 -> 975000 | G42: =(F42*$E$2) -> 48750 | H42: =$E$5*F42 -> 146250 | I42: =+(SUM(F42:H42)/(1-$E$3)) -> 1329545.5 | J42: =I42*E42 -> 1329545.5 | P42: =((8000/12)*65)*36 -> 1560000 | R42: =J42*$E$3 -> 159545.45
B43: 32 | C43: Service | D43: VPN | E43: 0 | F43: =(600*36)*100 -> 2160000 | G43: =(F43*$E$2) -> 108000 | H43: =$E$5*F43 -> 324000 | I43: =+(SUM(F43:H43)/(1-$E$3)) -> 2945454.5 | J43: =I43*E43 -> 0 | P43: =(300*36)*100 -> 1080000 | R43: =J43*$E$3 -> 0
B44: 33 | C44: Service | D44: GitLab Self Managed Premium License | E44: 10 | F44: =3*31500 -> 94500 | G44: =F44+(F44*$E$2) -> 99225 | H44: =F44*$E$4+F44 -> 111510 | I44: =+(SUM(F44:H44)/(1-$E$3)) -> 346857.95 | J44: =I44*E44 -> 3468579.5 | P44: =F44*E44 -> 945000 | R44: =J44*$E$3 -> 416229.55
B45: 33 | C45: Service | D45: Fortran / Intel OneAPI / HPC Tool Kit | E45: 6 | G45: =(F45*$E$2) -> 0 | H45: =$E$5*F45 -> 0 | I45: =+(SUM(F45:H45)/(1-$E$3)) -> 0 | J45: =I45*E45 -> 0 | P45: =F45*E45 -> 0 | R45: =J45*$E$3 -> 0
B46: 34 | C46: Software | D46: Monitoring Software - eNlight 360 | E46: 1 | F46: =(1500*36)*30 -> 1620000 | G46: =(F46*$E$2) -> 81000 | H46: =$E$5*F46 -> 243000 | I46: =+(SUM(F46:H46)/(1-$E$3)) -> 2209090.9 | J46: =I46*E46 -> 2209090.9 | P46: =(387*36)*65 -> 905580 | R46: =J46*$E$3 -> 265090.91
B47: Total Software and Services Cost | F47: =SUM(F22:F46) -> 44019922 | I47: =SUM(I22:I46) -> 60245161 | J47: =SUM(J22:J46) -> 1.0329622e+08 | L47: =J47*1.18 -> 1.2188954e+08 | M47: =L47-J47 -> 18593320 | P47: =SUM(P22:P46) -> 72839920 | R47: =SUM(R26:R46) -> 12395547
I51: without CPC | J51: =J20+J47 -> 2.5503296e+08
E52: 2.5413028e+08 | I52: with CPC | J52: =(J51/(1-0.12))+'Monthly Recurring'!H19 -> 3.0895441e+08
E53: 2.2481128e+08 | J53: =J52-J51 -> 53921449
E54: =E52-E53 -> 29318994 | J54: =J52*12% -> 37074529

Sheet Profitability
E1: Duration | F1: 36 | J1: Int Rate | K1: 0.08
J2: Total Inflow | K2: =C11-SUM(C9:C10) -> 2.654592e+08
B3: Profitability Summary | F3: Cash Flow | J3: Total Outflow | K3: =SUM(C13:C18)-SUM(C16:C17) -> 2.2156743e+08
B4: Particulars | C4: Amt ( in Rs) | D4: % | F4: Events | G4: payment % | H4: No of Months | I4: Inflow | J4: intial investment | K4: Net Inflow | L4: Interest Cost
B5: Selling Price | F5: 50% of Hardware Delivery | G5: 0.4 | H5: 2 | I5: =$K$2*G5 -> 1.0618368e+08 | J5: =-K3 -> -2.2156743e+08 | K5: =SUM(I5:J5) -> -1.1538375e+08 | L5: =K5*K1*H5/12 -> -1538450
B6: Hardware/server | C6: =Working!K20 -> 1.7568551e+08 | D6: =SUM(C6:C8)/C11 -> 0.93273367 | F6: 60% on completion of installation | G6: 0.5 | H6: 3 | I6: =$K$2*G6 -> 1.327296e+08 | K6: =K5+I6 -> 17345853
B7: Software | C7: =Working!K48 -> 88333690 | F7: 10% will be released after six months of acceptance sign-off | G7: 0.1 | H7: 6 | I7: =$K$2*G7 -> 26545920 | K7: =K6+I7 -> 43891773
B8: Broad Band | C8: =F19 -> 1440000 | F8: Finance Cost | L8: =SUM(L5:L7) -> -1538450
B9: Managed Services | C9: ='Monthly Recurring'!I17 -> 0
B10: MRC | C10: ='Monthly Recurring'!H17*F1 -> 19144228
B11: Total Contract Value | C11: =SUM(C6:C10) -> 2.8460343e+08 | F11: Notes:
B12: Input Cost | F12: 1. Overhead % will be consider as 10%
B13: Hardware/server | C13: =Working!Q20 -> 1.1406932e+08
B14: Software | C14: =Working!Q48 -> 56651596
B15: Broad Band | C15: =C8*0.8 -> 1152000
B16: Managed Services
B17: MRC | C17: ='Monthly Recurring'!S16*F1 -> 7075301.9
B18: CPC | C18: =Working!S20+Working!S48 -> 49694512 | F18: BroadBand
B19: Total Input Cost | C19: =SUM(C13:C18) -> 2.2864273e+08 | F19: 1440000
B20: Gross Profit / ( Loss ) | C20: =C11-C19 -> 55960698
B21: Less: Cash Overheads -H&S | C21: =(C19-SUM(C16:C18))*D21 -> 17187292 | D21: 0.1
B22: Less: Cash Overheads -MS | C22: =SUM(C16:C17)*D22 -> 2476355.7 | D22: 0.35
B23: EBITDA | C23: =C20-SUM(C21:C22) -> 36297051 | D23: =C23/C11 -> 0.12753554
B25: Interest charge on payment terms | C25: =L8 -> -1538450
B26: Net Profit | C26: =SUM(C23:C25) -> 34758601 | D26: =C26/C11 -> 0.12212994
B28: Gross Profit Margin | C28: =C20/C11 -> 0.19662693
B29: Net Profit Margin | C29: =C26/C11 -> 0.12212994
B30: Markup Percentage | C30: =(C11-C19)/C19 -> 0.24475171
B36: Profit % = (Total Contract Value- Total Input Cost)/ Total Input Cost | C36: =(C11-C19)/C19 -> 0.24475171
B37: Margin % = (Total Contract Value- Total Input Cost)/ Total Contract Value | C37: =(C11-C19)/C11 -> 0.19662693
B44: IaaS capex cost shifted to dep
B45: Overhead 25% charged on dep also
B46: Server and costbackup working required for actual capex and direct overhead charges
B47: Interest cost
B48: Rent and power

Sheet Components
B2: Product description | C2: Quantity | D2: Component Description | E2: Component Quantity
B3: ThinkAgile HX630 V3 Certified Node | C3: 1
D4: ThinkAgile HX630 V3 Base | E4: 1
D5: Data Center Environment 30 Degree Celsius / 86 Degree Fahrenheit | E5: 1
D6: XClarity Pro | E6: 1
D7: Nutanix SW Stack on Nutanix AHV | E7: 1
D8: 3 Years | E8: 1
D9: ThinkAgile HX Remote Deployment | E9: 1
D10: None | E10: 1
D11: Intel Xeon Gold 6542Y 24C 250W 2.9GHz Processor | E11: 2
D12: ThinkSystem 64GB TruDDR5 5600MHz (2Rx4) RDIMM | E12: 16
D13: ThinkSystem 1U 10x2.5" NVMe Backplane | E13: 1
D14: Nutanix Flash Node Config | E14: 1
D15: ThinkSystem 2.5" U.2 Solidigm P5520 7.68TB Read Intensive NVMe PCIe 4.0 x4 HS SSD | E15: 6
... D71: ThinkSystem 1U Super Cap Holder Dummy | E71: 1
B72: XClarity Controller Platin-FOD | C72: 1
D73: Lenovo XClarity XCC2 Platinum Upgrade (FOD) | E73: 1
B74: XClarity Pro, Per Endpoint w/5 Yr SW S&S | C74: 1
D75: Lenovo XClarity Pro, Per Managed Endpoint w/3 Yr SW S&S | E75: 1
D76: Registration only | E76: 1
B77: 3Yr Premier 24x7 4Hr Resp ThinkAgile CN HX630 V3 | C77: 1
B78: 3Yr KYD Add-On ThinkAgile CN HX630 V3 | C78: 1
B79: Hardware Installation Standard Server (Business Hours) | C79: 1
B80: ThinkAgile HX Remote Deployment (up to 3 node cluster) | C80: 1
B81: ThinkSystem External USB DVD-RW Optical Disk Drive | C81: 1
B83: ThinkAgile HX650 V3 Certified Node-HX | C83: 3
D84: ThinkAgile HX650 V3 Base | E84: 1
D85: Data Center Environment 30 Degree Celsius / 86 Degree Fahrenheit | E85: 1
D86: XClarity Pro | E86: 1
D87: Nutanix SW Stack on Nutanix AHV | E87: 1
D88: 3 Years | E88: 1
D89: ThinkAgile HX Onsite Deployment | E89: 1
D90: None | E90: 1
D91: Intel Xeon Gold 6542Y 24C 250W 2.9GHz Processor | E91: 2
D92: ThinkSystem 64GB TruDDR5 5600MHz (2Rx4) RDIMM | E92: 24
D93: ThinkSystem 2U/4U 8x2.5" NVMe Backplane | E93: 2
D94: Nutanix Flash Node Config | E94: 1
D95: ThinkSystem 2.5" U.2 Solidigm P5520 7.68TB Read Intensive NVMe PCIe 4.0 x4 HS SSD | E95: 8
... D158: ThinkSystem 8x1 2.5" HDD Filler | E158: 1
B159: XClarity Controller Platin-FOD | C159: 3
D160: Lenovo XClarity XCC2 Platinum Upgrade (FOD) | E160: 1
B161: XClarity Pro, Per Endpoint w/3 Yr SW S&S | C161: 3
D162: Lenovo XClarity Pro, Per Managed Endpoint w/3 Yr SW S&S | E162: 1
D163: Registration only | E163: 1
B164: 3Yr Premier 24x7 4Hr Resp ThinkAgile CN HX650 V3 | C164: 3
B165: ThinkAgile HX Onsite Deployment (up to 3 node cluster) | C165: 1
B166: ThinkSystem External USB DVD-RW Optical Disk Drive | C166: 3
B167: 2.8m, 13A/100-250V, C13 to C14 Jumper Cord | C167: 6
B170: Product description | C170: Quantity
B171: Extended 2Y HW support & 2Y Nutanix License - HX 630 Node | C171: 1
B172: Extended 2Y HW support & 2Y Nutanix License - HX 650 Node | C172: 3
B175: Nutanix License | C175: Cores
B176: Product
B177: Nutanix Cloud Infrastructure Pro, Production Support Per Core | C177: 192
B178: Nutanix Cloud Manager Starter, Production Support Per Core | C178: 192

Sheet Lenovo Quote
A1: Product Description | C1: Qty | D1: Price | E1: Total Part Price
D2: (per unit) Indian Rupee | E2: (quantity x unit price) Indian Rupee
A4: Server : ThinkAgile HX650 V3 Certified Node | C4: 8 | D4: =E4/C4+85875 -> 6880868.6 | E4: 54359949
A5: ThinkAgile HX650 V3 Base | C5: 8
A6: Data Center Environment 30 Degree Celsius / 86 Degree Fahrenheit | C6: 8
A7: XClarity Pro | C7: 8
A8: Nutanix SW Stack on Nutanix AHV | C8: 8
A9: 3 Years | C9: 8
A10: ThinkAgile HX Remote Deployment | C10: 8
A11: None | C11: 8
A12: Intel Xeon Gold 6542Y 24C 250W 2.9GHz Processor | C12: 16
A13: ThinkSystem 64GB TruDDR5 5600MHz (2Rx4) RDIMM | C13: 192
A14: ThinkSystem 440-16i SAS/SATA PCIe Gen4 12Gb Internal HBA | C14: 8
A15: ThinkSystem 2U 8x2.5" SAS/SATA Backplane | C15: 8
A16: ThinkSystem 2U/4U 8x2.5" AnyBay Backplane | C16: 8
... A81: Configuration ID 01 | C81: 8
A82: Auto-Derived Part Items
A83: ThinkSystem V3 2U x16/x8/x8 PCIe Gen4 Riser1 or 2 | C83: 8
A85: XClarity Pro, Per Endpoint w/3 Yr SW S&S | C85: 8
A86: Lenovo XClarity Pro, Per Managed Endpoint w/3 Yr SW S&S | C86: 8
A87: Registration only | C87: 8
A89: Configuration Instruction | C89: 8
A90: ThinkSystem 440-16i SAS/SATA PCIe Gen4 12Gb Internal HBA Placement | C90: 8
A91: Controller 01 | C91: 8
A92: Configuration ID 01 | C92: 8
A94: XClarity Controller Platin-FOD | C94: 8
A95: Lenovo XClarity XCC2 Platinum Upgrade (FOD) | C95: 8
A97: 3Yr Premier 24x7 4Hr Resp ThinkAgile CN HX650 V3 | C97: 8
A99: 3Yr KYD Add-On ThinkAgile CN HX650 V3 | C99: 8
... A105: ThinkAgile HX Remote Deployment (additional node) | C105: 5
A107: Standalone Items
A108: ThinkSystem External USB DVD-RW Optical Disk Drive | C108: 8
A110: Product Description | C110: Qty
A111: NCI – PRO :- Nutanix Cloud Infrastructure (NCI) Pro Software License - 3Y subscription | C111: 384
A112: NCM-Starter :- Nutanix Cloud Manager (NCM) Starter Software License - 3Y subscription | C112: 384
A113: NCI-ADR :- Nutanix Cloud Infrastructure (NCI) Advanced Replication (DC 352 + DR 384) - 3Y subscription | C113: 736
A116: Product Description | C116: Qty | D116: Price | E116: Total Part Price
A117: Storage : Lenovo ThinkSystem DG5200 QLC All Flash Array | C117: 1 | D117: =E117/C117 -> 32768967 | E117: 32768967
A118: Lenovo ThinkSystem Storage 2U NVMe Chassis | C118: 1
A119: Storage Complete Bundle Offering | C119: 1
A120: Lenovo ThinkSystem DM/DG5200 Series Controller, 64GB | C120: 2
A121: Lenovo ThinkSystem 61.4TB (2x 30.72TB QLC NVMe SED) Drive Pack for DG5200/DG7200 | C121: 12
A122: Lenovo ThinkSystem Storage 100Gb 2 port Ethernet (Host/Cluster) | C122: 2
A123: Lenovo ThinkSystem Storage 10/25Gb 2 port Ethernet (Host) | C123: 2
A124: Lenovo ThinkSystem Storage 64/32Gb 4 Port Fiber Channel Adapter | C124: 2
A125: 10G SW Optical iSCSI SFP+ Module 1 pack | C125: 4
A126: Lenovo 32Gb FC SFP+ Transceiver | C126: 4
A127: Lenovo 1m Passive 100G QSFP28 DAC Cable | C127: 2
A128: USB-A to USB-C Cable | C128: 1
A129: 2.8m, 13A/100-250V, C13 to C14 Jumper Cord | C129: 2
... A163: 3Yr Premier 24x7 4Hr Resp+KYD (0.1TB NVme QLC) | C163: 7373
A167: Product description | C167: Quantity | D167: Unit Price | E167: Total Price
A168: Extended 2Y HW support & 2Y Nutanix License - HX 650 Node | C168: 8 | D168: =E168/C168 -> 1746648.8 | E168: 13973190
A169: Extended 2Y Storage HW support | C169: 1 | D169: =E169/C169 -> 2000000 | E169: 2000000
A172: Product Description | C172: Qty | D172: Price | E172: Total Part Price
D173: (per unit) Indian Rupee | E173: (quantity x unit price) Indian Rupee
A175: Lenovo ThinkSystem DG5200 QLC All Flash Array | C175: 1 | D175: =E175/C175 -> 19323942 | E175: 19323942 | G175: 19523942
A176: Lenovo ThinkSystem Storage 2U NVMe Chassis | C176: 1
A177: Storage Complete Bundle Offering | C177: 1
A178: Lenovo ThinkSystem DM/DG5200 Series Controller, 64GB | C178: 2
A179: Lenovo ThinkSystem 30.7TB (2x 15.36TB QLC NVMe SED) Drive Pack | C179: 12 | G179: =30.7*12 -> 368.4
A180: Lenovo ThinkSystem Storage 100Gb 2 port Ethernet (Host/Cluster) | C180: 2
A181: Lenovo ThinkSystem Storage 10/25Gb 2 port Ethernet (Host) | C181: 2
A182: Lenovo ThinkSystem Storage 64/32Gb 4 Port Fiber Channel Adapter | C182: 2
A183: 10G SW Optical iSCSI SFP+ Module 1 pack | C183: 4
A184: Lenovo 32Gb FC SFP+ Transceiver | C184: 4
A185: Lenovo 1m Passive 100G QSFP28 DAC Cable | C185: 2
A186: Lenovo 5m LC-LC OM4 MMF Cable | C186: 8
A187: USB-A to USB-C Cable | C187: 1
A188: 2.8m, 13A/100-250V, C13 to C14 Jumper Cord | C188: 2
A189: Lenovo ThinkSystem Storage ONTAP 9.16 Software Encryption - IPAv2 | C189: 1
A190: 3 Years | C190: 1
A191: Premier 24x7 4hr with Enhanced Storage Support and KYD | C191: 1
... A221: 3Yr Premier 24x7 4Hr Resp+KYD (0.1TB NVme QLC) | C221: 3686

Sheet Sheet1
A1: Product description | B1: Quantity | C1: Component Description | D1: Component Quantity | E1: Nested In | F1: Unit Price | G1: Total Price
A2: ThinkAgile HX630 V3 Certified Node | B2: 1 | F2: =G2/B2 -> 5432892.2 | G2: 5432892.2
C3: ThinkAgile HX630 V3 Base | D3: 1
C4: Data Center Environment 30 Degree Celsius / 86 Degree Fahrenheit | D4: 1
C5: XClarity Pro | D5: 1
C6: Nutanix SW Stack on Nutanix AHV | D6: 1
C7: 3 Years | D7: 1
C8: ThinkAgile HX Remote Deployment | D8: 1
C9: None | D9: 1
C10: Intel Xeon Gold 6542Y 24C 250W 2.9GHz Processor | D10: 2
C11: ThinkSystem 64GB TruDDR5 5600MHz (2Rx4) RDIMM | D11: 16
C12: ThinkSystem 1U 10x2.5" NVMe Backplane | D12: 1
C13: Nutanix Flash Node Config | D13: 1
C14: ThinkSystem 2.5" U.2 Solidigm P5520 7.68TB Read Intensive NVMe PCIe 4.0 x4 HS SSD | D14: 6
... C70: ThinkSystem 1U Super Cap Holder Dummy | D70: 1
A71: XClarity Controller Platin-FOD | B71: 1 | E71: 1
C72: Lenovo XClarity XCC2 Platinum Upgrade (FOD) | D72: 1
A73: XClarity Pro, Per Endpoint w/5 Yr SW S&S | B73: 1 | E73: 1
C74: Lenovo XClarity Pro, Per Managed Endpoint w/3 Yr SW S&S | D74: 1
C75: Registration only | D75: 1
A76: 3Yr Premier 24x7 4Hr Resp ThinkAgile CN HX630 V3 | B76: 1 | E76: 1
A77: 3Yr KYD Add-On ThinkAgile CN HX630 V3 | B77: 1 | E77: 1
A78: Hardware Installation Standard Server (Business Hours) | B78: 1 | E78: 1
A79: ThinkAgile HX Remote Deployment (up to 3 node cluster) | B79: 1
A80: ThinkSystem External USB DVD-RW Optical Disk Drive | B80: 1
A82: ThinkAgile HX650 V3 Certified Node-HX | B82: 3 | F82: =G82/B82 -> 6146892.2 | G82: 18440677
C83: ThinkAgile HX650 V3 Base | D83: 1
C84: Data Center Environment 30 Degree Celsius / 86 Degree Fahrenheit | D84: 1
C85: XClarity Pro | D85: 1
C86: Nutanix SW Stack on Nutanix AHV | D86: 1
C87: 3 Years | D87: 1
C88: ThinkAgile HX Onsite Deployment | D88: 1
C89: None | D89: 1
C90: Intel Xeon Gold 6542Y 24C 250W 2.9GHz Processor | D90: 2
C91: ThinkSystem 64GB TruDDR5 5600MHz (2Rx4) RDIMM | D91: 24
C92: ThinkSystem 2U/4U 8x2.5" NVMe Backplane | D92: 2
C93: Nutanix Flash Node Config | D93: 1
C94: ThinkSystem 2.5" U.2 Solidigm P5520 7.68TB Read Intensive NVMe PCIe 4.0 x4 HS SSD | D94: 8
... C157: ThinkSystem 8x1 2.5" HDD Filler | D157: 1
A158: XClarity Controller Platin-FOD | B158: 3 | E158: 9
C159: Lenovo XClarity XCC2 Platinum Upgrade (FOD) | D159: 1
A160: XClarity Pro, Per Endpoint w/3 Yr SW S&S | B160: 3 | E160: 9
C161: Lenovo XClarity Pro, Per Managed Endpoint w/3 Yr SW S&S | D161: 1
C162: Registration only | D162: 1
A163: 3Yr Premier 24x7 4Hr Resp ThinkAgile CN HX650 V3 | B163: 3 | E163: 9
A164: ThinkAgile HX Onsite Deployment (up to 3 node cluster) | B164: 1
A165: ThinkSystem External USB DVD-RW Optical Disk Drive | B165: 3
A166: 2.8m, 13A/100-250V, C13 to C14 Jumper Cord | B166: 6
F167: Total in INR | G167: =G2+G82 -> 23873569
A169: Product description | B169: Quantity | F169: Unit Price | G169: Total Price
A170: Extended 2Y HW support & 2Y Nutanix License - HX 630 Node | B170: 1 | F170: =G170/B170 -> 2796192.2 | G170: 2796192.2
A171: Extended 2Y HW support & 2Y Nutanix License - HX 650 Node | B171: 3 | F171: =G171/B171 -> 2914716.2 | G171: 8744148.6
F172: Total in INR | G172: =SUM(G170:G171) -> 11540341
A174: Nutanix License | B174: Cores
A175: Product
A176: Nutanix Cloud Infrastructure Pro, Production Support Per Core | B176: 192
A177: Nutanix Cloud Manager Starter, Production Support Per Core | B177: 192

Sheet Redington
B2: Program | C2: Part Number | D2: Item Name | E2: DTP | F2: Estimate Retail Price | G2: Product Type
B3: Open Value | C3: 395-03274 | D3: Exchange Server Ent SLng LSA OLV NL 3Y Aq Y1 AP | E3: 613005.25 | F3: 769209 | G3: License/Software Assurance Pack
B4: Open Value | C4: 7NQ-00162 | D4: SQL Server Standard Core SLng LSA OLV 2L NL 3Y Aq Y1 AP | E4: 519184.5 | F4: 651483 | G4: License/Software Assurance Pack
B5: Open Value | C5: 9EM-00513 | D5: Win Server Standard Core SLng LSA OLV 16L NL 3Y Aq Y1 AP | E5: 154801.75 | F5: 194250 | G5: License/Software Assurance Pack
B7: Part Number | C7: Item Name | D7: DTP | E7: Estimate Retail Price | F7: Purchase Unit | G7: Agreement Duration | H7: License Agreement Type
B8: 312-03039 | C8: Exchange Server Standard SLng LSA OLV NL 1Y Aq Y3 AP | D8: 78148.63 | E8: 98063 | F8: 1 Year(s) | G8: 1 Year | H8: Corporate
B9: 395-03278 | C9: Exchange Server Ent SLng LSA OLV NL 1Y Aq Y3 AP | D9: 437855.25 | E9: 549428 | F9: 1 Year(s) | G9: 1 Year | H9: Corporate
B11: ProductId | C11: SkuTitle | D11: DTP | E11: ERP | F11: Segment
B12: DG7GMGF0F4MF | C12: Exchange Server Enterprise 2019 | D12: 331753.25 | E12: 378589 | F12: Commercial
B13: DG7GMGF0F4MD | C13: Exchange Server Enterprise 2019 Device CAL | D13: 3499.03 | E13: 3993 | F13: Commercial
B14: DG7GMGF0F4MD | C14: Exchange Server Enterprise 2019 User CAL | D14: 4466.45 | E14: 5097 | F14: Commercial
B15: DG7GMGF0F4MC | C15: Exchange Server Standard 2019 | D15: 58071.65 | E15: 66270 | F15: Commercial
B16: DG7GMGF0F4MB | C16: Exchange Server Standard 2019 Device CAL | D16: 5583.72 | E16: 6372 | F16: Commercial
B17: DG7GMGF0F4MB | C17: Exchange Server Standard 2019 User CAL | D17: 7221.5 | E17: 8241 | F17: Commercial
B19: Item | C19: Quantity | D19: Type
B20: Exchange Server 2019 Standard or Enterprise | C20: 1 | D20: Perpetual
B21: Exchange Server Standard CAL | C21: 500 | D21: Perpetual
B22: Exchange Server Enterprise CAL Add-on | C22: 500 | D22: Perpetual
B23: Software Assurance for Exchange Server 2019 | C23: 1 | D23: SA Add-on
B24: Microsoft Defender for Exchange (Optional) | C24: 500 | D24: Subscription (CSP)
B26: ProductTitle | C26: ProductId | D26: Billing Cycle | E26: MRP | F26: DTP | G26: Final_TP
E27: (Per Unit Annual) | F27: (Per Unit Annual) | G27: (Per Unit Annual)
B28: Microsoft Defender for Office 365 (Plan 1) | C28: CFQ7TTC0LH04 | D28: Annual | E28: 1980 | F28: 1584 | G28: 1584
B29: Microsoft Defender for Office 365 (Plan 2) | C29: CFQ7TTC0LHXH | E29: 4980 | F29: 3984 | G29: 3984

Sheet RHEL
B2: SKU | C2: Description | D2: Term | E2: Qty | F2: Price per unit | G2: Total Price
B3: RH00232 | C3: Red Hat Enterprise Linux Server for Service Providers, Full Support (Physical or Virtual Nodes, Dedicated, Yearly) | D3: ANNUAL | E3: 10 | F3: 72672.6 | G3: 7,26,726.00
B4: RH00236 | C4: Red Hat Enterprise Linux Server for Service Providers, Diagnostic Support (Physical or Virtual Nodes, Dedicated, Yearly) | D4: ANNUAL | E4: 10 | F4: 60560.5 | G4: 6,05,605.00
B5: RH00777 | C5: Red Hat Enterprise Linux, Extended Life Cycle Support Add-On, Layered Support (Physical or Virtual Nodes, Dedicated, Yearly) | D5: ANNUAL | E5: 4 | F5: 27987.96 | G5: 1,11,951.84
C8: Per year Avg Server license | D8: 80182.102
C9: Per year Avg Support license | D9: 66818.418
C10: Per year avg ELS license | D10: 30880.049

Sheet Cyberdristi
B2: Sr. No. | C2: Line Item | D2: Quantity | E2: Unit Price Per Annum in INR | F2: Partner transfer Price – Total/year in INR
B3: 1 | C3: PAM Admin User-based License | D3: 20 | E3: 32000 | F3: =E3*D3 -> 640000
B4: 2 | C4: PAM End User-based License | D4: 300 | E4: 900 | F4: ₹ 2,70,000/-
B5: 3 | C5: DLP User-based License | D5: 60 | E5: 5000 | F5: ₹ 3,00,000/-
B6: 4 | C6: One-time Setup Cost | D6: - | E6: - | F6: ₹ 3,00,000/-
C7: Annual Support Plan [Professional] | D7: 1 Year | E7: - | F7: ₹ 3,60,000/-
B8: Total (Excluding Taxes) in INR | F8: 1670000

Sheet OEM
A1: Redington Windows
B2: Program | C2: Part Number | D2: Item Name | E2: DTP | F2: Estimate Retail Price | G2: Product Type
B3: Open Value | C3: 395-03274 | D3: Exchange Server Ent SLng LSA OLV NL 3Y Aq Y1 AP | E3: 613005.25 | F3: 769209 | G3: License/Software Assurance Pack
B4: Open Value | C4: 7NQ-00162 | D4: SQL Server Standard Core SLng LSA OLV 2L NL 3Y Aq Y1 AP | E4: 519184.5 | F4: 651483 | G4: License/Software Assurance Pack
B5: Open Value | C5: 9EM-00513 | D5: Win Server Standard Core SLng LSA OLV 16L NL 3Y Aq Y1 AP | E5: 154801.75 | F5: 194250 | G5: License/Software Assurance Pack
B7: Part Number | C7: Item Name | D7: DTP | E7: Estimate Retail Price | F7: Purchase Unit | G7: Agreement Duration | H7: License Agreement Type
B8: 312-03039 | C8: Exchange Server Standard SLng LSA OLV NL 1Y Aq Y3 AP | D8: 78148.63 | E8: 98063 | F8: 1 Year(s) | G8: 1 Year | H8: Corporate
B9: 395-03278 | C9: Exchange Server Ent SLng LSA OLV NL 1Y Aq Y3 AP | D9: 437855.25 | E9: 549428 | F9: 1 Year(s) | G9: 1 Year | H9: Corporate
B11: ProductId | C11: SkuTitle | D11: DTP | E11: ERP | F11: Segment
B12: DG7GMGF0F4MF | C12: Exchange Server Enterprise 2019 | D12: 331753.25 | E12: 378589 | F12: Commercial
B13: DG7GMGF0F4MD | C13: Exchange Server Enterprise 2019 Device CAL | D13: 3499.03 | E13: 3993 | F13: Commercial
B14: DG7GMGF0F4MD | C14: Exchange Server Enterprise 2019 User CAL | D14: 4466.45 | E14: 5097 | F14: Commercial
B15: DG7GMGF0F4MC | C15: Exchange Server Standard 2019 | D15: 58071.65 | E15: 66270 | F15: Commercial
B16: DG7GMGF0F4MB | C16: Exchange Server Standard 2019 Device CAL | D16: 5583.72 | E16: 6372 | F16: Commercial
B17: DG7GMGF0F4MB | C17: Exchange Server Standard 2019 User CAL | D17: 7221.5 | E17: 8241 | F17: Commercial
B19: Item | C19: Quantity | D19: Type
B20: Exchange Server 2019 Standard or Enterprise | C20: 1 | D20: Perpetual
B21: Exchange Server Standard CAL | C21: 500 | D21: Perpetual
B22: Exchange Server Enterprise CAL Add-on | C22: 500 | D22: Perpetual
B23: Software Assurance for Exchange Server 2019 | C23: 1 | D23: SA Add-on
B24: Microsoft Defender for Exchange (Optional) | C24: 500 | D24: Subscription (CSP)
B26: ProductTitle | C26: ProductId | D26: Billing Cycle | E26: MRP | F26: DTP | G26: Final_TP
E27: (Per Unit Annual) | F27: (Per Unit Annual) | G27: (Per Unit Annual)
B28: Microsoft Defender for Office 365 (Plan 1) | C28: CFQ7TTC0LH04 | D28: Annual | E28: 1980 | F28: 1584 | G28: 1584
B29: Microsoft Defender for Office 365 (Plan 2) | C29: CFQ7TTC0LHXH | E29: 4980 | F29: 3984 | G29: 3984
A31: Ingrammicro
B32: SKU | C32: Description | D32: Term | E32: Qty | F32: Price per unit | G32: Total Price
B33: RH00232 | C33: Red Hat Enterprise Linux Server for Service Providers, Full Support (Physical or Virtual Nodes, Dedicated, Yearly) | D33: ANNUAL | E33: 10 | F33: 72672.6 | G33: 7,26,726.00
B34: RH00236 | C34: Red Hat Enterprise Linux Server for Service Providers, Diagnostic Support (Physical or Virtual Nodes, Dedicated, Yearly) | D34: ANNUAL | E34: 10 | F34: 60560.5 | G34: 6,05,605.00
B35: RH00777 | C35: Red Hat Enterprise Linux, Extended Life Cycle Support Add-On, Layered Support (Physical or Virtual Nodes, Dedicated, Yearly) | D35: ANNUAL | E35: 4 | F35: 27987.96 | G35: 1,11,951.84
C38: Per year Avg Server license | D38: 80182.102
C39: Per year Avg Support license | D39: 66818.418
C40: Per year avg ELS license | D40: 30880.049
A42: Cyberdristi Pam DLP
B43: Sr. No. | C43: Line Item | D43: Quantity | E43: Unit Price Per Annum in INR | F43: Partner transfer Price – Total/year in INR
B44: 1 | C44: PAM Admin User-based License | D44: 20 | E44: 32000 | F44: =E44*D44 -> 640000
B45: 2 | C45: PAM End User-based License | D45: 300 | E45: 900 | F45: ₹ 2,70,000/-
B46: 3 | C46: DLP User-based License | D46: 60 | E46: 5000 | F46: ₹ 3,00,000/-
B47: 4 | C47: One-time Setup Cost | D47: - | E47: - | F47: ₹ 3,00,000/-
C48: Annual Support Plan [Professional] | D48: 1 Year | E48: - | F48: ₹ 3,60,000/-
B49: Total (Excluding Taxes) in INR | F49: 1670000
A51: Fineshift GitLab
B52: # | C52: Item & Description | D52: HSN/SAC | E52: Qty | F52: Rate | G52: CGST | H52: SGST | I52: Amount
B53: 1 | C53: GitLab Self Managed Premium License | D53: 85238020 | E53: 10 | F53: 31,200.00 | G53: 9% | H53: 9% | I53: 3,12,000.00
C54: Term 1st Year
B55: 2 | C55: GitLab Self Managed Premium License | D55: 85238020 | E55: 10 | F55: 31,200.00 | G55: 9% | H55: 9% | I55: 3,12,000.00
C56: Term 2nd Year
B57: 3 | C57: GitLab Self Managed Premium License | D57: 85238020 | E57: 10 | F57: 31,200.00 | G57: 9% | H57: 9% | I57: 3,12,000.00
C58: Term 3rd Year
G59: Sub Total | I59: 9,36,000.00
B60: Total In Words Indian Rupee Eleven Lakh Four Thousand Four Hundred Eighty Only | G60: CGST9 (9%) | I60: 84,240.00
G61: SGST9 (9%) | I61: 84,240.00
B62: Notes | G62: Total | I62: ₹11,04,480.00
B64: Cisco
A65: Line Number | B65: Part Number | C65: Description | D65: Service Duration | E65: Estimated Lead | F65: Qty | G65: Unit Price INR | H65: Total Price iNR
D66: (Months) | E66: Time (Days)
A68: 1 | B68: C9300-24T-E | C68: Catalyst 9300 24-port data only, Network Essentials | D68: --- | E68: 7 | F68: 2 | G68: 158806.72 | H68: 317613.44 | I68: L3 Switch
A69: 1.0.1 | B69: CON-SNT-C93002TE | C69: SNTC-8X5XNBD Catalyst 9300 24-port data only, Network | D69: 36 | E69: N/A | F69: 2 | G69: 56680.18 | H69: 113360.37
A70: 1.1 | B70: C9300-DNA-E-24 | C70: C9300 DNA Essentials, 24-Port Term Licenses | D70: --- | E70: 14 | F70: 2 | G70: - | H70: -
A71: 1.1.1 | B71: C9300-DNA-E-24-3Y | C71: C9300 DNA Essentials, 24-Port, 3 Year Term License | D71: 36 | E71: N/A | F71: 2 | G71: 20375.99 | H71: 40751.99
A72: 1.2 | B72: C9300-NW-E-24 | C72: C9300 Network Essentials, 24-port license | D72: --- | E72: 14 | F72: 2 | G72: - | H72: -
A73: 1.3 | B73: SC9300UK9-1712 | C73: Cisco Catalyst 9300 XE 17.12 UNIVERSAL | D73: --- | E73: 14 | F73: 2 | G73: - | H73: -
A74: 1.4 | B74: PWR-C1-350WAC-P | C74: 350W AC 80+ platinum Config 1 Power Supply | D74: --- | E74: 14 | F74: 2 | G74: - | H74: -
A75: 1.5 | B75: PWR-C1-350WAC-P/2 | C75: 350W AC 80+ platinum Config 1 Secondary Power Supply | D75: --- | E75: 14 | F75: 2 | G75: 18708.57 | H75: 37417.14
A76: 1.6 | B76: CAB-TA-IN | C76: India AC Type A Power Cable | D76: --- | E76: 14 | F76: 4 | G76: - | H76: -
A77: 1.7 | B77: C9300-SSD-NONE | C77: No SSD Card Selected | D77: --- | E77: 14 | F77: 2 | G77: - | H77: -
A78: 1.8 | B78: STACK-T1-50CM | C78: 50CM Type 1 Stacking Cable | D78: --- | E78: 14 | F78: 2 | G78: 2878.21 | H78: 5756.41
A79: 1.9 | B79: CAB-SPWR-30CM | C79: Catalyst Stack Power Cable 30 CM | D79: --- | E79: 14 | F79: 2 | G79: 2734.41 | H79: 5468.83
A80: 1.1 | B80: C9K-ACC-RBFT | C80: RUBBER FEET FOR TABLE TOP SETUP 9200 and 93xx | D80: --- | E80: 14 | F80: 2 | G80: - | H80: -
A81: 1.11 | B81: C9K-ACC-SCR-4 | C81: 12-24 and 10-32 SCREWS FOR RACK INSTALLATION, QTY 4 | D81: --- | E81: 14 | F81: 2 | G81: - | H81: -
A82: 1.12 | B82: CAB-GUIDE-1RU | C82: 1RU CABLE MANAGEMENT GUIDES 9200 and 9300 | D82: --- | E82: 14 | F82: 2 | G82: - | H82: -
A83: 1.13 | B83: C9300-NM-8X | C83: Catalyst 9300 8 x 10GE Network Module | D83: --- | E83: 14 | F83: 2 | G83: 73395.41 | H83: 146790.82 | I83: Unit
A84: 1.14 | B84: NETWORK-PNP-LIC | C84: Network Plug-n-Play Connect for zero-touch device deployment | D84: --- | E84: 3 | F84: 2 | G84: - | H84: =SUM(H68:H83) -> 667159 | I84: =H84/2 -> 333579.5
A85: 2 | B85: C9300X-24Y-E | C85: Catalyst 9300X 24x25G Fiber Ports, modular uplink Switch | D85: --- | E85: 7 | F85: 1 | G85: 932634.36 | H85: 932634.36 | I85: L3 switch
A86: 2.0.1 | B86: CON-SNT-C9300XYE | C86: SNTC-8X5XNBD Catalyst 9300X 24x25G Fiber Ports, modul | D86: 36 | E86: N/A | F86: 1 | G86: 299244.04 | H86: 299244.04
A87: 2.1 | B87: C9300X-DNA-24Y-E | C87: C9300 DNA Essentials, Term License | D87: --- | E87: 14 | F87: 1 | G87: - | H87: -
A88: 2.1.1 | B88: C9300-DNA-L-E-3Y | C88: DNA Essentials 3 Year License | D88: 36 | E88: N/A | F88: 1 | G88: 39393.57 | H88: 39393.57
A89: 2.2 | B89: D-DNAS-EXT-S-T | C89: Cisco DNA Spaces Extend Term License for Catalyst Switches | D89: --- | E89: 14 | F89: 1 | G89: - | H89: -
A90: 2.2.1 | B90: D-DNAS-EXT-S-3Y | C90: Cisco DNA Spaces Extend for Catalyst Switching - 3Year | D90: 36 | E90: N/A | F90: 1 | G90: - | H90: -
A91: 2.3 | B91: SC9300UK9-1715 | C91: CAT9300/9400/9500/9600 UNIVERSAL | D91: --- | E91: 14 | F91: 1 | G91: - | H91: -
A92: 2.4 | B92: PWR-C1-715WAC-P | C92: 715W AC 80+ platinum Config 1 Power Supply | D92: --- | E92: 14 | F92: 1 | G92: - | H92: -
A93: 2.5 | B93: C9300-SPS-NONE | C93: No Secondary Power Supply Selected | D93: --- | E93: 14 | F93: 1 | G93: - | H93: -
A94: 2.6 | B94: CAB-TA-IN | C94: India AC Type A Power Cable | D94: --- | E94: 14 | F94: 1 | G94: - | H94: -
A95: 2.7 | B95: C9300X-NW-E-24 | C95: C9300 Network Essentials, 24-port license | D95: --- | E95: 14 | F95: 1 | G95: - | H95: -
A96: 2.8 | B96: STACK-T1-50CM | C96: 50CM Type 1 Stacking Cable | D96: --- | E96: 14 | F96: 1 | G96: 2878.21 | H96: 2878.21
A97: 2.9 | B97: C9300-SPWR-NONE | C97: No Stack Power Cable Selected | D97: --- | E97: 14 | F97: 1 | G97: - | H97: -
A98: 2.1 | B98: C9300-SSD-NONE | C98: No SSD Card Selected | D98: --- | E98: 14 | F98: 1 | G98: - | H98: -
A99: 2.11 | B99: C9K-ACC-RBFT | C99: RUBBER FEET FOR TABLE TOP SETUP 9200 and 93xx | D99: --- | E99: 14 | F99: 1 | G99: - | H99: -
A100: 2.12 | B100: C9K-ACC-SCR-4 | C100: 12-24 and 10-32 SCREWS FOR RACK INSTALLATION, QTY 4 | D100: --- | E100: 14 | F100: 1 | G100: - | H100: -
A101: 2.13 | B101: CAB-GUIDE-1RU | C101: 1RU CABLE MANAGEMENT GUIDES 9200 and 9300 | D101: --- | E101: 14 | F101: 1 | G101: - | H101: -
A102: 2.14 | B102: C9300X-NM-8Y | C102: Catalyst 9300 8 x 10G/25G Network Module SFP+/SFP28 | D102: --- | E102: 14 | F102: 1 | G102: 67523.78 | H102: 67523.78
A103: 2.15 | B103: NETWORK-PNP-LIC | C103: Network Plug-n-Play Connect for zero-touch device deployment | D103: --- | E103: 3 | F103: 1 | G103: - | H103: -
H104: =SUM(H85:H102) -> 1341674 | I104: =H104/2 -> 670836.98
A105: 3 | B105: C9200L-24T-4G-E | C105: Catalyst 9200L 24-port data only, 4 x 1G, Network Essentials | D105: --- | E105: 7 | F105: 2 | G105: 67808.11 | H105: 67808.11 | I105: L2 Switch
A106: 3.0.1 | B106: CON-SNT-C920L24T | C106: SNTC-8X5XNBD Catalyst 9200L 24-port data, 4 x 1G, Net | D106: 36 | E106: N/A | F106: 2 | G106: 24720.75 | H106: 24720.75
A107: 3.1 | B107: C9200L-DNA-E-24 | C107: C9200L Cisco DNA Essentials, 24-port Term license | D107: --- | E107: 14 | F107: 2 | G107: - | H107: -
A108: 3.1.1 | B108: C9200L-DNA-E-24-3Y | C108: C9200L Cisco DNA Essentials, 24-port, 3 Year Term license | D108: 36 | E108: N/A | F108: 2 | G108: 20376.84 | H108: 20376.84
A109: 3.2 | B109: C9200L-NW-E-24 | C109: C9200L Network Essentials, 24-port license | D109: --- | E109: 14 | F109: 2 | G109: - | H109: -
A110: 3.3 | B110: CAB-TA-IN | C110: India AC Type A Power Cable | D110: --- | E110: 14 | F110: 2 | G110: - | H110: -
A111: 3.4 | B111: PWR-C5-BLANK | C111: Config 5 Power Supply Blank | D111: --- | E111: 14 | F111: 2 | G111: - | H111: -
...

Sheet Payment term
B2: 8.9 Payment Terms & Milestones:
B3: a. Payment shall be made on completion of each Milestone and would be at the discretion of IBPS within one month on submission of invoice. | D3: Sr No. | E3: Activity | F3: Timeline to achieve Milestone | G3: Outcome | H3: Project Milestone
B4: b. Listed below Table consist of the activities and timelines for Completion of Milestones. | D4: Date of issue of contract. This is being referred to as ’T’ in the timeline column of this table.
B5: c. Payment shall only be made after satisfactory completion of issued Milestone / submission of report / delivery of items & licenses and due certification to the effect by IBPS. | D5: 1 | E5: Project Initiation & Planning | F5: T | G5: Requirements, Scope, Timelines | H5: Start of Milestone 1
B6: Each Bill shall be accompanied with the following information: | D6: 2 | E6: DR Design Finalized | F6: T + 2 Weeks | G6: Approved Architecture & Design Docs
B7: a. Work done satisfactory certificates signed jointly by IBPS and the System Integrator. | D7: 3 | E7: Procurement & Provisioning | F7: T + 4 Weeks | G7: Resources Available
B8: b. Submission of Invoice | D8: 4 | E8: Delivery of the Equipment’s (Hardware and Software) at DR | F8: T + 5 Weeks | G8: Acceptance by IBPS of Receiving the Equipment
B9: c. 40% Payment shall be made to the System Integrator after completion of Milestone 1, and with software licence with other necessary components delivered at DR Site shall be mentioned in the Purchase Order issued. | D9: 5 | E9: Submission of DR Handover Plan "HO Plan" | F9: T + 6 Weeks | G9: Acceptance for Complete Milestone 1 and issuance of acceptance certificate subject to completion of complete work as per RFP. | H9: Completion of Milestone 1
B10: d. 50% Payment shall be made on completion of Milestone 2 and after acceptance sign-off from IBPS. | D10: 5 | E10: Pre - Installation, Sample - Testing & Commissioning of Complete Equipment at DR. | F10: T + 6 Weeks | G10: Acceptance Testing (AT) to IBPS as per Acceptance Testing Plan (ATP) | H10: Start of Milestone 2
B11: e. Post completion of Milestone 3, Balance amount of 10% will be released after six (6) months of acceptance sign-off from IBPS and solution implemented working smoothly. | D11: 4 | E11: Infrastructure Implementation | F11: T + 6 Weeks | G11: DR Infrastructure Built & Replicating
D12: 5 | E12: DR Testing Completed | F12: T + 7 Weeks | G12: Verified Failover/Failback
D13: 6 | E13: Test Result Documentation | F13: T + 7 Weeks | G13: All Critical Issue Fixed
D14: 7 | E14: Resolution and Revaluation | F14: T + 8 Weeks | G14: Runbook Update (If any)
D15: 8 | E15: Environmental Sync and Monitoring Setup | F15: T + 8 Weeks | G15: Business Users Validate
D16: 9 | E16: SOPs / Runbooks Finalized | F16: T + 8 Weeks | G16: Operational Readiness Documents
D17: 10 | E17: Go-Live and Stage 2 Sign Off | F17: T + 8 Weeks | G17: DR Infra Operational | H17: Completion of Milestone 2
D18: 11 | E18: Knowledge Transfer and Training | F18: T + 9 Weeks | G18: User to be Trained | H18: Start of Milestone 3
D19: 12 | E19: Governance & Ongoing Maintenance | F19: T + 10 Weeks | G19: Regular Drills, Reviews, Audits
D20: 13 | E20: Final Sign off | F20: T + 11 Weeks | G20: Completion of DR Setup | H20: Completion of Milestone 3

Sheet Line-item wise prices
B2: Sr No | C2: Description | D2: Qty | E2: Unit Price | F2: Total Price | G2: Tax | H2: Total With Tax
B3: 1 | C3: Router (2 Units) | D3: 2
B4: 2 | C4: L3 Switch (2 units + line cards) | D4: 2
B5: 3 | C5: Firewalls (2 units) | D5: 2
C6: Secure VPN for 50 User | D6: 1
B7: 4 | C7: L2 Switch | D7: 2
B8: 5 | C8: Load Balancer and WAF | D8: 1
B9: 6 | C9: Nutanix HCI Nodes | D9: 8
B10: 7 | C10: SAN | D10: 1
B11: 8 | C11: NAS Devices | D11: 3
B12: 9 | C12: Antivirus with DLP (50 users) | D12: 1
B13: 10 | C13: Linux Licenses (17) + Database (3) | D13: 1
B14: 11 | C14: Windows Licenses (13) + Database (12) | D14: 1
B15: 12 | C15: XDR (50 endpoints) | D15: 1
B16: 13 | C16: Blackbox Storage | D16: 1
B17: 14 | C17: SIEM | D17: 1
B18: 15 | C18: Intel Fortran (6 Licenses) | D18: 1
... B21: 18 | C21: Exchange Server | D21: 1
B22: 19 | C22: Implementation
B23: 20 | C23: Migration of Resources from DC to DR
B24: 21 | C24: Cloud DC & DR, Connectivity
B25: 22 | C25: Managed Services (03+02Years)
B26: 23 | C26: Other
B27: 24 | C27: Other
C28: TOTAL

Sheet Technical Scoring Matrix Criter
B2: Sl No | C2: Evaluation Criteria | D2: Documents Required | E2: Max Mark | F2: Yes/No
B3: 1 | C3: The CSP Annual Average turnover form Cloud Service business in India during the last 3 financial years. 200 Crores to <= 225 Crores – 5 Marks 225 Crores to <= 250 Crores – 10 Marks >250 Crores – 15 Marks | D3: • Audited statement for last 3 financial years of the System Integrator (SI). • Certificate from the Chartered Accountant/ statutory auditor/ Company Secretary clearly specifying the annual turnover from the operations of Cloud Service business. | E3: 15
B4: 2 | C4: The CSP shall have successfully deployed and provided Data Centre/ Disaster recovery/ Cloud Services for any Govt. organisation/ PSU in India within last 7 Years with combined project value of: | D4: Copy of Work orders/Client Certificate/Agreement | E4: 10
B5: 2 | C5: 5 Crores to < 10 Crores – 5 Marks | D5: Copy of Work orders/Client Certificate/Agreement | E5: 10
B6: 2 | C6: 10 Crores to <= 15 Crores – 7 Marks | D6: Copy of Work orders/Client Certificate/Agreement | E6: 10
B7: 2 | C7: >15 Crores – 10 Marks | D7: Copy of Work orders/Client Certificate/Agreement | E7: 10
B8: 3 | C8: The CSP shall have successfully deployed and provided Data Centre/ Disaster recovery/ Cloud Services for any Govt. Organization/ PSU in India within last 7 Years: | D8: Copy of Work orders/Client Certificate/Agreement | E8: 10
B9: 3 | C9: 3 to <= 5 projects – 5 Marks | D9: Copy of Work orders/Client Certificate/Agreement | E9: 10
B10: 3 | C10: 5 to <= 7 projects – 7 Marks | D10: Copy of Work orders/Client Certificate/Agreement | E10: 10
B11: 3 | C11: >7 projects – 10 Marks | D11: Copy of Work orders/Client Certificate/Agreement | E11: 10
B12: 4 | C12: The CSP should have of the following Certifications valid at the time of Bidding: | D12: Valid Certificate(s) by the relevant certifying agency. | E12: 10
B13: 4 | C13: 1. ISO 9001 | D13: Valid Certificate(s) by the relevant certifying agency. | E13: 10
B14: 4 | C14: 2. ISO 27001 | D14: Valid Certificate(s) by the relevant certifying agency. | E14: 10
... B21: 4 | C21: 9. CMMI 3 or above | D21: Valid Certificate(s) by the relevant certifying agency. | E21: 10
C22: For Sr.1 to 6 Certificates – 5 Marks
C23: For Sr. 1 to 8 Certificates – 7 Marks for Sr. 1 -9 Certificates – 10 Marks
B24: 5 | C24: The CSP must be operating from Data Centres in Mumbai Region and all of them should be empanelled by MeitY. 1 Data Centre: 5 Marks 2 Data Centre: 10 marks | D24: Letter from Authorized signatory on the letter head of the CSP confirming Data Centre location and MeitY empanelment. | E24: 10
B25: 6 | C25: The CSP should have ability to provide following security components / procedures if needed: | D25: Valid Certificate(s) by the relevant certifying agency. | E25: 15
B26: 6 | C26: 1. Isolation of virtual environments from security and networking perspective | D26: Self-Undertaking of consent for Physical audit of Data Centre. | E26: 15
B27: 6 | C27: 2. Multi-factor Authentication | E27: 15
B28: 6 | C28: 3. Identity and Access Management | E28: 15
B29: 6 | C29: 4. Data Encryption at rest and in motion | E29: 15
B30: 6 | C30: 5. Key Management | E30: 15
B31: 6 | C31: 6. Physical Audit of Data Center on Demand | E31: 15
B32: 6 | C32: 7. Web Application Firewall | E32: 15
B33: 6 | C33: 8. DDoS Protection | E33: 15
B34: 6 | E34: 15
B35: 6 | C35: 3 to <=5 Components/Procedures – 5 Marks | E35: 15
B36: 6 | C36: 5 to <=7 Components/Procedures -- 10 Marks All 8 Components/Procedures – 15 Marks | E36: 15
B37: 7 | C37: Technical Proposal solution Approach and Methodology Including but not limited to: | D37: Technical Proposal & Methodology | E37: 30
B38: 7 | C38: a) Detailed understanding of Scope of Work requirements -5 Marks | D38: Technical Proposal & Methodology | E38: 30
B39: 7 | C39: b) Disaster Recovery (DR) and Business Continuity Plan (BCP) --5 Marks | D39: Technical Proposal & Methodology | E39: 30
B40: 7 | C40: c) Security Architecture and Data Protection--5 Marks | D40: Technical Proposal & Methodology | E40: 30
B41: 7 | C41: d) Training and Knowledge Transfer Plan--5 Marks | D41: Technical Proposal & Methodology | E41: 30
B42: 7 | C42: e) Integration and Interoperability Plan--5 Marks | D42: Technical Proposal & Methodology | E42: 30
B43: 7 | C43: f) Scalability and Future-readiness--5 Marks | D43: Technical Proposal & Methodology | E43: 30
D44: Total | E44: 100

Sheet Broadband Cost
D2: GST | E2: 0.3
B3: Speed | C3: 50
B4: OTC | C4: 25000 | D4: =C4*1.18 -> 29500 | E4: =D4+(D4*$E$2) -> 38350
B5: ARC | C5: 300000 | D5: =C5*1.18 -> 354000 | E5: =D5+(D5*$E$2) -> 460200 | F5: =36*F6 -> 1440000
B6: MRC | C6: =C5/12 -> 25000 | D6: =C6*1.18 -> 29500 | E6: =D6+(D6*$E$2) -> 38350 | F6: 40000
B7: MRC/Mb | C7: =C6/C3 -> 500 | D7: =C7*1.18 -> 590 | E7: =D7+(D7*$E$2) -> 767

Sheet Windows Server
A1: Sr. No. | B1: Details | C1: Physical or Virtual? | D1: CPU Cores | E1: RAM (GB) | F1: Storage Space | G1: SSD/SAS? | H1: HOST OS
A2: 1 | B2: WServer1 | C2: Virtual | D2: 16 | E2: 32 | F2: =1.27*1024 -> 1300.48 | G2: SSD | H2: Windows 2019 STD
A3: 2 | B3: WServer2 | C3: Virtual | D3: 8 | E3: 64 | F3: =3.42*1024 -> 3502.08 | G3: SSD | H3: Windows 2019 STD
A4: 3 | B4: WServer3 | C4: Virtual | D4: 4 | E4: 32 | F4: 470 | G4: SSD | H4: Windows 2019 STD
A5: 4 | B5: WServer4 | C5: Virtual | D5: 4 | E5: 16 | F5: 105.33 | G5: SSD | H5: Windows 2019 STD
A6: 5 | B6: WServer5 | C6: Virtual | D6: 2 | E6: 32 | F6: =2.2*1024 -> 2252.8 | G6: SSD | H6: Windows 2019 STD
A7: 6 | B7: WServer6 | C7: Virtual | D7: 8 | E7: 64 | F7: 800 | G7: SSD | H7: Windows 2019 STD
A8: 7 | B8: WServer7 | C8: Virtual | D8: 8 | E8: 32 | F8: =4.25*1024 -> 4352 | G8: SSD | H8: Windows 2019 STD
A9: 8 | B9: WServer8 | C9: Virtual | D9: 4 | E9: 32 | F9: 600 | G9: SSD | H9: Windows 2019 STD
A10: 9 | B10: WServer9 | C10: Virtual | D10: 4 | E10: 64 | F10: 900 | G10: SSD | H10: Windows 2019 STD
A11: 10 | B11: WServer10 | C11: Virtual | D11: 4 | E11: 32 | F11: =1.22*1024 -> 1249.28 | G11: SSD | H11: Windows 2019 STD
A12: 11 | B12: WServer11 | C12: Virtual | D12: 8 | E12: 64 | F12: =2.56*1024 -> 2621.44 | G12: SSD | H12: Windows 2019 STD
A13: 12 | B13: WServer12 | C13: Virtual | D13: 8 | E13: 16 | F13: 100 | G13: SSD | H13: Windows 2019 STD
A14: 13 | B14: WServer13 | C14: Virtual | D14: 4 | E14: 64 | F14: =2.73*1024 -> 2795.52 | G14: SSD | H14: Windows 2019 STD
A15: 14 | B15: WServer14 | C15: Virtual | D15: 4 | E15: 16 | F15: =8.11*1024 -> 8304.64 | G15: SSD | H15: Windows 2019 STD
A16: 15 | B16: WServer15 | C16: Virtual | D16: 4 | E16: 32 | F16: 600.31 | G16: SSD | H16: Windows 2019 STD
A17: 16 | B17: WServer16 | C17: Virtual | D17: 8 | E17: 64 | F17: 900 | G17: SSD | H17: Windows 2019 STD
A18: 17 | B18: WServer17 | C18: Virtual | D18: 16 | E18: 32 | F18: =1.95*1024 -> 1996.8 | G18: SSD | H18: Windows 2019 STD
A19: 18 | B19: WServer18 | C19: Virtual | D19: 8 | E19: 32 | F19: =2.68*1024 -> 2744.32 | G19: SSD | H19: Windows 2019 STD
A20: 19 | B20: WServer19 | C20: Virtual | D20: 4 | E20: 32 | F20: =1.5*1024 -> 1536 | G20: SSD | H20: Windows 2019 STD
A21: 20 | B21: Wserver20 | C21: Virtual | D21: 2 | E21: 16 | F21: 150 | G21: SSD | H21: Windows 2019 STD
A22: 21 | B22: Wserver21 | C22: Virtual | D22: 16 | E22: 95 | F22: =5.68*1024 -> 5816.32 | G22: SSD | H22: Windows 2019 STD
A23: 22 | B23: Wserver22 | C23: Virtual | D23: 16 | E23: 95 | F23: =6.68*1024 -> 6840.32 | G23: SSD | H23: Windows 2019 STD
A24: 23 | B24: Wserver23 | C24: Virtual | D24: 2 | E24: 8 | F24: 150 | G24: SSD | H24: Windows 2019 STD
A25: 24 | B25: Wserver24 | C25: * Virtual | D25: 4 | E25: 32 | F25: =1*1024 -> 1024 | G25: SAS | H25: Windows 2019 STD
A26: 25 | B26: Wserver25 | C26: * Virtual | D26: 16 | E26: 256 | F26: =3*1024 -> 3072 | G26: SAS | H26: Windows 2012 STD
A27: 26 | B27: Wserver26 | C27: * Virtual | D27: 12 | E27: 64 | F27: =1*1024 -> 1024 | G27: SAS | H27: Windows 2012 R2 STD
A28: 27 | B28: Wserver27 | C28: * Virtual | D28: 12 | E28: 32 | F28: =1*1024 -> 1024 | G28: HDD | H28: Windows 2012 STD
A29: 28 | B29: Wserver28 | C29: * Virtual | D29: 4 | E29: 32 | F29: =1*1024 -> 1024 | G29: SSD | H29: Windows 2019 STD
A30: 29 | B30: Wserver29 | C30: * Virtual | D30: 4 | E30: 32 | F30: 300 | G30: HDD | H30: Windows 2012 STD
A31: 30 | B31: Wserver30 | C31: * Virtual | D31: 12 | E31: 32 | F31: =2.1*1024 -> 2150.4 | G31: HDD | H31: Windows 2012 STD
A32: 31 | B32: Wserver31 | C32: * Virtual | D32: 12 | E32: 32 | F32: =2.1*1024 -> 2150.4 | G32: HDD | H32: Windows 2012 STD
D33: =SUM(D2:D32) -> 238

Sheet Colo
B2: Sr. No. | C2: Description | D2: Qty | E2: Rate | F2: Amount | G2: Remark
B3: 1 | C3: Cage for 2 Racks | D3: 80 Sqft. | E3: 18,00 | F3: 126000 | G3: OTC | H3: OTC
B4: 2 | C4: Racks with Metered iPDUs (1-phase 32 A- 2 Nos. on each rack) | D4: 2 Nos. | E4: 160000 | F4: 325000 | G4: OTC | H4: OTC
B5: 3 | C5: Rack Space Charges | D5: 2 Nos. | E5: 21000 | F5: =42000 -> 42000 | G5: MRC
B6: 4 | C6: CCTV | D6: 2 Nos. | E6: 18000 | F6: 36000 | G6: OTC | H6: OTC
B7: 5 | C7: Biometric for each rack and cage entry/exit | D7: 4 Nos. | E7: 50000 | F7: 200000 | G7: OTC | H7: OTC
B8: 6 | C8: Power Tariff kVA | D8: 28 | E8: 15500 | F8: =D8*E8 -> 434000 | G8: MRC | H8: =F3+F4+F6+F7 -> 687000 | I8: =H8/8 -> 85875
F10: =SUM(F3:F8) -> 1163000 | H10: 15% margin
G11: =F8+F5 -> 476000 | H11: =G11*60 -> 28560000
E12: Power | F12: =SUM(F3,F4,F6,F7) -> 687000 | G12: =(F5*1.15)+F8 -> 482300
C13: Router | D13: 2 | E13: 800 | F13: =E13*D13 -> 1600
C14: L3 Switch | D14: 2 | E14: 800 | F14: =E14*D14 -> 1600
C15: L2 Switch | D15: 2 | E15: 800 | F15: =E15*D15 -> 1600
C16: FC Switch | D16: 1 | E16: 800 | F16: =E16*D16 -> 800
C17: Server | D17: 8 | E17: 1600 | F17: =E17*D17 -> 12800
C18: Uified Storage | D18: 1 | E18: 1600 | F18: =E18*D18 -> 1600
C19: NAS | D19: 3 | E19: 800 | F19: =E19*D19 -> 2400
F20: =SUM(F13:F19) -> 22400
G21: 28kVA | H21: =18000*28 -> 504000

Sheet Discount Sheet
E2: 0 | G2: 0
A3: Discount Sheet
B4: Enterprise Storage & Backup Space (IaaS) | C4: UNIT | D4: COST/UNIT | E4: DISCOUNT (%) | F4: COST/UNIT | G4: GeM feee | H4: COST/UNIT incl GeM fee
A5: Iaas | B5: vCPU 1P- 2vCPU | C5: 1 | D5: 162 | E5: 0 | F5: =(D5-(D5*E5%)) -> 162 | G5: =(F5*$G$2) -> 0 | H5: =F5+G5 -> 162
A6: Iaas | B6: vRAM | C6: 1 | D6: 162 | E6: 0 | F6: =(D6-(D6*E6%)) -> 162 | G6: =(F6*$G$2) -> 0 | H6: =F6+G6 -> 162
A7: Iaas | B7: IOPS | C7: 1 | D7: 2 | E7: 0 | F7: =(D7-(D7*E7%)) -> 2 | G7: =(F7*$G$2) -> 0 | H7: =F7+G7 -> 2
A8: Iaas | B8: Block Storage | C8: 1 | D8: 3 | E8: 0 | F8: =(D8-(D8*E8%)) -> 3 | G8: =(F8*$G$2) -> 0 | H8: =F8+G8 -> 3
A9: Iaas | B9: 1 GB of Storage Space - 1000 IOPs/per TB | C9: 1 | D9: 3 | E9: 0 | F9: =(D9-(D9*E9%)) -> 3 | G9: =(F9*$G$2) -> 0 | H9: =F9+G9 -> 3
A10: Iaas | B10: 1 GB of Storage Space - 3000 IOPs/per TB | C10: 1 | D10: 9 | E10: 0 | F10: =(D10-(D10*E10%)) -> 9 | G10: =(F10*$G$2) -> 0 | H10: =F10+G10 -> 9
A11: Iaas | B11: 1 TB of Storage Space - 10000 IOPs/per TB | C11: 1 | D11: 20 | E11: 0 | F11: =(D11-(D11*E11%)) -> 20 | G11: =(F11*$G$2) -> 0 | H11: =F11+G11 -> 20
A12: Iaas | B12: 1 TB of Storage Space - 300 IOPs/per TB | C12: 1 | D12: 2000 | E12: 0 | F12: =(D12-(D12*E12%)) -> 2000 | G12: =(F12*$G$2) -> 0 | H12: =F12+G12 -> 2000
A13: Iaas | B13: 1 TB Performance Storage Space - 1000 IOPs/per TB | C13: 1 | D13: 3000 | E13: 0 | F13: =(D13-(D13*E13%)) -> 3000 | G13: =(F13*$G$2) -> 0 | H13: =F13+G13 -> 3000
A14: Iaas | B14: 1 TB Performance Storage Storage Space - 3000 IOPs/per TB | C14: 1 | D14: 4000 | E14: 0 | F14: =(D14-(D14*E14%)) -> 4000 | G14: =(F14*$G$2) -> 0 | H14: =F14+G14 -> 4000
A15: Iaas | B15: Object Storage - (For All Virtual Instance) | C15: 1 | D15: 3.17 | E15: 0 | F15: =(D15-(D15*E15%)) -> 3.17 | G15: =(F15*$G$2) -> 0 | H15: =F15+G15 -> 3.17
A16: Iaas | B16: Archive Storage - (For All Virtual Instance) | C16: 1 | D16: 2 | E16: 0 | F16: =(D16-(D16*E16%)) -> 2 | G16: =(F16*$G$2) -> 0 | H16: =F16+G16 -> 2
... A18: Iaas | B18: Backup Storage - (For All Virtual Instance) | C18: 1 | D18: 4000 | E18: 0 | F18: =(D18-(D18*E18%)) -> 4000 | G18: =(F18*$G$2) -> 0 | H18: =F18+G18 -> 4000
A19: B.2 | B19: Software as Service (SaaS) | C19: UNIT | D19: COST/UNIT | E19: DISCOUNT (%) | F19: COST/UNIT | G19: GST | H19: COST/UNIT incl GST
A20: OS | B20: Windows Server 2012/ 2016/ 2019 Standard Edition | C20: 1 | D20: 700 | E20: 0 | F20: =(D20-(D20*E20%)) -> 700 | G20: =(F20*$G$2) -> 0 | H20: =F20+G20 -> 700
A21: OS | B21: CentOS/ Ubuntu | C21: 1 | D21: Freeware | E21: Freeware | F21: Freeware | G21: Freeware | H21: Freeware
A22: DB | B22: MSSQL STD | C22: 1 | D22: 17914 | E22: 0 | F22: =(D22-(D22*E22%)) -> 17914 | G22: =(F22*$G$2) -> 0 | H22: =F22+G22 -> 17914
A23: DB | B23: Oracle 19c SE | C23: 1 | D23: 38306 | E23: 0 | F23: =(D23-(D23*E23%)) -> 38306 | G23: =(F23*$G$2) -> 0 | H23: =F23+G23 -> 38306
A24: DB | B24: Oracle 19c EE | C24: 1 | D24: 180952 | E24: 0 | F24: =(D24-(D24*E24%)) -> 180952 | G24: =(F24*$G$2) -> 0 | H24: =F24+G24 -> 180952
A25: DB | B25: MSSQL Enterprise | C25: 1 | D25: 90000 | E25: 0 | F25: =(D25-(D25*E25%)) -> 90000 | G25: =(F25*$G$2) -> 0 | H25: =F25+G25 -> 90000
A26: DB | B26: RHEL | C26: 1 | D26: 5100 | E26: 0 | F26: =(D26-(D26*E26%)) -> 5100 | G26: =(F26*$G$2) -> 0 | H26: =F26+G26 -> 5100
A27: OS | B27: Backup Agent | C27: 1 | D27: 1000 | E27: 0 | F27: =(D27-(D27*E27%)) -> 1000 | G27: =(F27*$G$2) -> 0 | H27: =F27+G27 -> 1000
A28: OS | B28: cPanel/WHM | C28: 1 | D28: 2200 | E28: 0 | F28: =(D28-(D28*E28%)) -> 2200 | G28: =(F28*$G$2) -> 0 | H28: =F28+G28 -> 2200
A29: DB | B29: Database Performance Monitoring | C29: 1 | D29: 200 | E29: 0 | F29: =(D29-(D29*E29%)) -> 200 | G29: =(F29*$G$2) -> 0 | H29: =F29+G29 -> 200
A30: B.2 | B30: Security As Service | C30: UNIT | D30: COST/UNIT | E30: DISCOUNT (%) | F30: COST/UNIT | G30: GST | H30: COST/UNIT incl GST
A31: Service | B31: Virtual External Firewall 1 Gbps throughput | C31: 1 | D31: 26500 | E31: 0 | F31: =(D31-(D31*E31%)) -> 26500 | G31: =(F31*$G$2) -> 0 | H31: =F31+G31 -> 26500
A32: Service | B32: Internal Virtual Firewall 1 Gbps throughput | C32: 1 | D32: 15000 | E32: 0 | F32: =(D32-(D32*E32%)) -> 15000 | G32: =(F32*$G$2) -> 0 | H32: =F32+G32 -> 15000
A33: Service | B33: vUTM- Internal Security | C33: 1 | D33: 16500 | E33: 0 | F33: =(D33-(D33*E33%)) -> 16500 | G33: =(F33*$G$2) -> 0 | H33: =F33+G33 -> 16500
A34: Service | B34: Haltdos vWAF 1000 Mbps | C34: 1 | D34: 61333 | E34: 0 | F34: =(D34-(D34*E34%)) -> 61333 | G34: =(F34*$G$2) -> 0 | H34: =F34+G34 -> 61333 | I34: Haltdos
A35: Service | B35: SSL Certificate : Domain Wildcard SSL | C35: 1 | D35: 4200 | E35: 0 | F35: =(D35-(D35*E35%)) -> 4200 | G35: =(F35*$G$2) -> 0 | H35: =F35+G35 -> 4200
A36: Service | B36: SSL Certificate : Domain SSL | C36: 1 | D36: 750 | E36: 0 | F36: =(D36-(D36*E36%)) -> 750 | G36: =(F36*$G$2) -> 0 | H36: =F36+G36 -> 750
A37: Service | B37: DDoS Mitigation as a Service -1 Gbps Mitigation | C37: 1 | D37: 18000 | E37: 0 | F37: =(D37-(D37*E37%)) -> 18000 | G37: =(F37*$G$2) -> 0 | H37: =F37+G37 -> 18000
A38: Service | B38: Antivirus + HIPS | C38: 1 | D38: 1400 | E38: 0 | F38: =(D38-(D38*E38%)) -> 1400 | G38: =(F38*$G$2) -> 0 | H38: =F38+G38 -> 1400
A39: Service | B39: Antivirus | C39: 1 | D39: 700 | E39: 0 | F39: =(D39-(D39*E39%)) -> 700 | G39: =(F39*$G$2) -> 0 | H39: =F39+G39 -> 700
A40: Service | B40: ESDS MFA - External Security | C40: 1 | D40: 500 | E40: 0 | F40: =(D40-(D40*E40%)) -> 500 | G40: =(F40*$G$2) -> 0 | H40: =F40+G40 -> 500
A41: Service | B41: EDR | C41: 1 | D41: 2200 | E41: 0 | F41: =(D41-(D41*E41%)) -> 2200 | G41: =(F41*$G$2) -> 0 | H41: =F41+G41 -> 2200
A42: Service | B42: PAM | C42: 1 | D42: 1200 | E42: 0 | F42: =(D42-(D42*E42%)) -> 1200 | G42: =(F42*$G$2) -> 0 | H42: =F42+G42 -> 1200
A43: Service | B43: SIEM | C43: 1 | D43: 2000 | E43: 0 | F43: =(D43-(D43*E43%)) -> 2000 | G43: =(F43*$G$2) -> 0 | H43: =F43+G43 -> 2000
A44: Service | B44: Enlight IAM | C44: 1 | D44: 100 | E44: 0 | F44: =(D44-(D44*E44%)) -> 100 | G44: =(F44*$G$2) -> 0 | H44: =F44+G44 -> 100
A45: Service | B45: VTM Scan - 4 Scan Monthly | C45: 1 | D45: 800 | E45: 0 | F45: =(D45-(D45*E45%)) -> 800 | G45: =(F45*$G$2) -> 0 | H45: =F45+G45 -> 800
A46: Service | B46: VAPT Audit CERT-IN- Quarterly | C46: 1 | D46: 4500 | E46: 0 | F46: =(D46-(D46*E46%)) -> 4500 | G46: =(F46*$G$2) -> 0 | H46: =F46+G46 -> 4500
... A48: Service | B48: Fortinet DLP Network External Security | C48: 1 | D48: 600 | E48: 0 | F48: =(D48-(D48*E48%)) -> 600 | G48: =(F48*$G$2) -> 0 | H48: =F48+G48 -> 600
A49: B.2 | B49: Network as Service | C49: UNIT | D49: COST/UNIT | E49: DISCOUNT (%) | F49: COST/UNIT | G49: GST | H49: COST/UNIT incl GST
A50: Service | B50: Unmetered Internet Bandwidth at Datacenter Site | C50: 1 | D50: 800 | E50: 0 | F50: =(D50-(D50*E50%)) -> 800 | G50: =(F50*$G$2) -> 0 | H50: =F50+G50 -> 800
A51: Service | B51: Volume based Internet bandwidth - per GB | C51: 1 | D51: 6 | E51: 0 | F51: =(D51-(D51*E51%)) -> 6 | G51: =(F51*$G$2) -> 0 | H51: =F51+G51 -> 6
A52: Service | B52: IPv6 | C52: 1 | D52: 1500 | E52: 0 | F52: =(D52-(D52*E52%)) -> 1500 | G52: =(F52*$G$2) -> 0 | H52: =F52+G52 -> 1500
A53: Service | B53: IPv4 | C53: 1 | D53: 900 | E53: 0 | F53: =(D53-(D53*E53%)) -> 900 | G53: =(F53*$G$2) -> 0 | H53: =F53+G53 -> 900
A54: Service | B54: Replication Link between DC - DR | C54: 1 | D54: 800 | E54: 0 | F54: =(D54-(D54*E54%)) -> 800 | G54: =(F54*$G$2) -> 0 | H54: =F54+G54 -> 800
A55: Service | B55: Cross Connect + Port Termination - 1 Gbps Fiber Port | C55: 1 | D55: 2100 | E55: 0 | F55: =(D55-(D55*E55%)) -> 2100 | G55: =(F55*$G$2) -> 0 | H55: =F55+G55 -> 2100
A56: Service | B56: SSL-VPN | C56: 1 | D56: 300 | E56: 0 | F56: =(D56-(D56*E56%)) -> 300 | G56: =(F56*$G$2) -> 0 | H56: =F56+G56 -> 300
A57: Service | B57: IPSEC-VPN - Connectivity | C57: 1 | D57: 500 | E57: 0 | F57: =(D57-(D57*E57%)) -> 500 | G57: =(F57*$G$2) -> 0 | H57: =F57+G57 -> 500
A58: Service | B58: gDNS | C58: 1 | D58: 1000 | E58: 0 | F58: =(D58-(D58*E58%)) -> 1000 | G58: =(F58*$G$2) -> 0 | H58: =F58+G58 -> 1000
A59: Service | B59: CDN as a service- per instance | C59: 1 | D59: 2700 | E59: 0 | F59: =(D59-(D59*E59%)) -> 2700 | G59: =(F59*$G$2) -> 0 | H59: =F59+G59 -> 2700
A60: B.3 | B60: Infra Monitoring and Mgmt and Other Services | C60: UNIT | D60: COST/UNIT | E60: DISCOUNT (%) | F60: COST/UNIT | G60: GST | H60: COST/UNIT incl GST
A61: Service | B61: Operating System Management | C61: 1 | D61: 1500 | E61: 0 | F61: =(D61-(D61*E61%)) -> 1500 | G61: =(F61*$G$2) -> 0 | H61: =F61+G61 -> 1500
A62: Service | B62: Database management - PostgreSQL and MySQL | C62: 1 | D62: 7500 | E62: 0 | F62: =(D62-(D62*E62%)) -> 7500 | G62: =(F62*$G$2) -> 0 | H62: =F62+G62 -> 7500
A63: Service | B63: Database management - MSSQL | C63: 1 | D63: 1000 | E63: 0 | F63: =(D63-(D63*E63%)) -> 1000 | G63: =(F63*$G$2) -> 0 | H63: =F63+G63 -> 1000
A64: Service | B64: MariaDB Database Managed Services (Up to 100 GB) | C64: 1 | D64: 7500 | E64: 0 | F64: =(D64-(D64*E64%)) -> 7500 | G64: =(F64*$G$2) -> 0 | H64: =F64+G64 -> 7500
A65: Service | B65: vUTM Firewall - Security Mng - Managed Services | C65: 1 | D65: 2000 | E65: 0 | F65: =(D65-(D65*E65%)) -> 2000 | G65: =(F65*$G$2) -> 0 | H65: =F65+G65 -> 2000
A66: Service | B66: Storage Management- per TB | C66: 1 | D66: 500 | E66: 0 | F66: =(D66-(D66*E66%)) -> 500 | G66: =(F66*$G$2) -> 0 | H66: =F66+G66 -> 500
A67: Service | B67: Backup Management - per VM | C67: 1 | D67: 1500 | E67: 0 | F67: =(D67-(D67*E67%)) -> 1500 | G67: =(F67*$G$2) -> 0 | H67: =F67+G67 -> 1500
A68: Service | B68: Patch Management | C68: 1 | D68: 500 | E68: 0 | F68: =(D68-(D68*E68%)) -> 500 | G68: =(F68*$G$2) -> 0 | H68: =F68+G68 -> 500
A69: Service | B69: Network Management | C69: 1 | D69: 3500 | E69: 0 | F69: =(D69-(D69*E69%)) -> 3500 | G69: =(F69*$G$2) -> 0 | H69: =F69+G69 -> 3500
A70: Service | B70: Security Management Service (Firewall) | C70: 1 | D70: 9500 | E70: 0 | F70: =(D70-(D70*E70%)) -> 9500 | G70: =(F70*$G$2) -> 0 | H70: =F70+G70 -> 9500
A71: Service | B71: Security Management Service (WAF) | C71: 1 | D71: 16500 | E71: 0 | F71: =(D71-(D71*E71%)) -> 16500 | G71: =(F71*$G$2) -> 0 | H71: =F71+G71 -> 16500
A72: Service | B72: SIEM Management | C72: 1 | D72: 100 | E72: 0 | F72: =(D72-(D72*E72%)) -> 100 | G72: =(F72*$G$2) -> 0 | H72: =F72+G72 -> 100
... A84: Service | B84: Application performance Monitoring | C84: 1 | D84: 750 | E84: 0 | F84: =(D84-(D84*E84%)) -> 750 | G84: =(F84*$G$2) -> 0 | H84: =F84+G84 -> 750
D85: =3000/50 -> 60 | F85: =3000/50 -> 60

Sheet Sheet4
C5: 1920 Network Insights (QNI) Appliance M7
C7: Partcode | D7: Renewal | E7: Description | F7: License Quantity | G7: Remarks
C8: D0DJ5ZX | D8: E0DJ4ZX | E8: IBM QRadar Network Insights Appliance 1920 G3 Appliance Install Appliance + Subscription and Support 12 Months | F8: 2 | G8: 1 Qty QNI 1920 Appliance
C9: D0DJ7ZX | D9: E0DJ8ZX | E9: IBM QRadar Network Insights Appliance 1920 G3 Appliance Install Initial Appliance Business Critical Service Upgrade 12 Months | F9: 2 | G9: Business Critical Service
C10: D0DJ9ZX | D10: E0DJAZX | E10: IBM QRadar Network Insights Appliance 1920 G3 Appliance Install Initial Appliance Hard Drive Retention Service Upgrade 12 Months | F10: 2 | G10: Hard Drive Retention Service
C14: Part Code | D14: Renewal | E14: Description | F14: License Quantity | G14: Remarks
C15: D0AE4ZX | D15: E0AE3ZX | E15: IBM Security QRadar Suite Software 100 Resource Unit License + Subscription & Support 12 Months | F15: 30 | G15: Qradar NDR
C16: D0AEIZX | D16: E0AEHZX | E16: IBM Security QRadar Suite Software Disaster Recovery 100 Resource Unit License + SW Subscription & Support 12 Months | F16: 30 | G16: Qradar NDR
